{
  "summary": {
    "version": {
      "patch_index": 1419,
      "version": "14.19"
    },
    "versions": [
      "14.19",
      "14.18",
      "14.17"
    ],
    "meta": {
      "id": 421,
      "key": "RekSai",
      "name": "虚空遁地兽",
      "image_url": "https://opgg-static.akamaized.net/meta/images/lol/latest/champion/RekSai.png",
      "evolve": [],
      "partype": "怒气",
      "passive": {
        "name": "艾克塞之怒",
        "description": "雷克塞可通过攻击和命中基础技能来生成怒气。她在位于地下时可消耗怒气来回复生命值。",
        "image_url": "https://opgg-static.akamaized.net/meta/images/lol/latest/passive/RekSai_Passive.png",
        "video_url": null
      },
      "spells": [
        {
          "key": "Q",
          "name": "女王之怒 / 猎物搜寻",
          "description": "雷克塞的下3次普攻会对身边的敌人造成额外物理伤害。<br><br>在地底时，雷克塞发射一道充满虚空能量的冲击波，对命中的敌人造成伤害并使其显形。",
          "max_rank": 5,
          "range_burn": [
            325
          ],
          "cooldown_burn": [
            4,
            3,
            3,
            2,
            2
          ],
          "cooldown_burn_float": [
            4,
            3.5,
            3,
            2.5,
            2
          ],
          "cost_burn": [
            0
          ],
          "tooltip": "<keywordMajor>位于地表：</keywordMajor>雷克塞在?秒内的下3次普攻会获得<attackSpeed>?%攻击速度</attackSpeed>并对附近的敌人造成额外的<physicalDamage>?物理伤害</physicalDamage>。攻击会刷新这个技能的持续时长。?",
          "image_url": "https://opgg-static.akamaized.net/meta/images/lol/latest/spell/RekSaiQ.png",
          "video_url": "https://d28xe8vt774jo5.cloudfront.net/champion-abilities/0421/ability_0421_Q1.webm"
        },
        {
          "key": "W",
          "name": "遁地 / 破土而出",
          "description": "雷克塞遁入地下，提供新的技能并提升移动速度。她的视野距离会被降低并且无法进行普攻。<br><br>在地底时，雷克塞可以施放破土而出，击飞并伤害身边的敌人。",
          "max_rank": 5,
          "range_burn": [
            1650
          ],
          "cooldown_burn": [
            4
          ],
          "cooldown_burn_float": [
            4
          ],
          "cost_burn": [
            0
          ],
          "tooltip": "<keywordMajor>位于地表：</keywordMajor>雷克塞遁入地下，获得全新的一套技能但不能攻击。她获得<speed>?移动速度</speed>，视野距离被降低?%，并且附近不可见的敌人在移动时会将其位置显形给雷克塞和她的友军。?",
          "image_url": "https://opgg-static.akamaized.net/meta/images/lol/latest/spell/RekSaiW.png",
          "video_url": "https://d28xe8vt774jo5.cloudfront.net/champion-abilities/0421/ability_0421_W1.webm"
        },
        {
          "key": "E",
          "name": "狂野之噬 / 挖掘隧道",
          "description": "雷克塞噬咬她的目标，可在满怒时造成额外伤害。<br><br>在地底时，雷克塞挖掘出一个可重复使用、长期存在的隧道。敌人可以通过踩在任一入口上来摧毁整条隧道。",
          "max_rank": 5,
          "range_burn": [
            250
          ],
          "cooldown_burn": [
            10
          ],
          "cooldown_burn_float": [
            10
          ],
          "cost_burn": [
            0
          ],
          "tooltip": "<scaleAD>位于地表：</scaleAD>雷克塞撕咬一个目标，造成<physicalDamage>?物理伤害</physicalDamage>。在满额<keywordMajor>怒气</keywordMajor>时，这次撕咬会造成额外的<physicalDamage>?%最大生命值物理伤害</physicalDamage>。?",
          "image_url": "https://opgg-static.akamaized.net/meta/images/lol/latest/spell/RekSaiE.png",
          "video_url": "https://d28xe8vt774jo5.cloudfront.net/champion-abilities/0421/ability_0421_E1.webm"
        },
        {
          "key": "R",
          "name": "虚空猛冲",
          "description": "雷克塞可通过伤害目标来将其标记。她可以激活这个技能，暂时变成不可被选取状态，并扑向一个被标记的目标，并基于其已损失生命值造成重度伤害。",
          "max_rank": 3,
          "range_burn": [
            1500
          ],
          "cooldown_burn": [
            100,
            90,
            80
          ],
          "cooldown_burn_float": [
            100,
            90,
            80
          ],
          "cost_burn": [
            0
          ],
          "tooltip": "雷克塞将一个在之前的?秒内被她造成过伤害的敌人选为目标，随后会遁入地下，变得无法被选取。片刻之后，她会不可阻挡地跃向目标，造成<physicalDamage>?加上?%已损失生命值的物理伤害</physicalDamage>。?",
          "image_url": "https://opgg-static.akamaized.net/meta/images/lol/latest/spell/RekSaiR.png",
          "video_url": "https://d28xe8vt774jo5.cloudfront.net/champion-abilities/0421/ability_0421_R1.webm"
        }
      ],
      "skins": [
        {
          "id": 421000,
          "champion_id": 421,
          "name": "default",
          "centered_image": "https://opgg-static.akamaized.net/meta/images/lol/latest/champion/centered/RekSai_0.jpg",
          "skin_video_url": null,
          "prices": [
            {
              "currency": "IP",
              "cost": 4800
            },
            {
              "currency": "RP",
              "cost": 880
            }
          ],
          "sales": null,
          "release_date": null
        },
        {
          "id": 421001,
          "champion_id": 421,
          "name": "上古战魂 雷克塞",
          "centered_image": "https://opgg-static.akamaized.net/meta/images/lol/latest/champion/centered/RekSai_1.jpg",
          "skin_video_url": "https://youtu.be/AHCuRYjlvRg",
          "prices": [
            {
              "currency": "RP",
              "cost": 1350
            }
          ],
          "sales": null,
          "release_date": "2014-12-11T08:00:00+09:00"
        },
        {
          "id": 421017,
          "champion_id": 421,
          "name": "永恒之森 雷克塞",
          "centered_image": "https://opgg-static.akamaized.net/meta/images/lol/latest/champion/centered/RekSai_17.jpg",
          "skin_video_url": "https://youtu.be/2yWlwP8OHsM",
          "prices": [
            {
              "currency": "RP",
              "cost": 1350
            }
          ],
          "sales": null,
          "release_date": "2022-01-06T04:00:00+09:00"
        },
        {
          "id": 421002,
          "champion_id": 421,
          "name": "泳池派对 雷克塞",
          "centered_image": "https://opgg-static.akamaized.net/meta/images/lol/latest/champion/centered/RekSai_2.jpg",
          "skin_video_url": "https://youtu.be/GGOrtjbpFO0",
          "prices": [
            {
              "currency": "RP",
              "cost": 1350
            }
          ],
          "sales": null,
          "release_date": "2015-06-24T23:00:00+09:00"
        },
        {
          "id": 421026,
          "champion_id": 421,
          "name": "海魔兽 雷克塞",
          "centered_image": "https://opgg-static.akamaized.net/meta/images/lol/latest/champion/centered/RekSai_26.jpg",
          "skin_video_url": null,
          "prices": [
            {
              "currency": "RP",
              "cost": 1350
            }
          ],
          "sales": null,
          "release_date": "2024-07-17T09:00:00+09:00"
        },
        {
          "id": 421009,
          "champion_id": 421,
          "name": "黯晶巨兽 雷克塞",
          "centered_image": "https://opgg-static.akamaized.net/meta/images/lol/latest/champion/centered/RekSai_9.jpg",
          "skin_video_url": "https://youtu.be/ufvOjGjowy8",
          "prices": [
            {
              "currency": "RP",
              "cost": 1350
            }
          ],
          "sales": null,
          "release_date": "2020-03-05T04:00:00+09:00"
        }
      ]
    },
    "summary": {
      "id": 421,
      "is_rotation": false,
      "is_rip": false,
      "average_stats": {
        "play": 211,
        "win_rate": 0.483412,
        "pick_rate": 0.0293868,
        "ban_rate": 0.0160443,
        "kda": 3.030185,
        "tier": 4,
        "rank": 142,
        "tier_data": {
          "tier": 4,
          "rank": 142,
          "rank_prev": 145,
          "rank_prev_patch": 109
        }
      },
      "positions": [
        {
          "name": "JUNGLE",
          "stats": {
            "play": 206,
            "win_rate": 0.490291,
            "pick_rate": 0.0272307,
            "role_rate": 0.976303,
            "ban_rate": 0.0156641,
            "kda": 3.082912,
            "tier_data": {
              "tier": 4,
              "rank": 31,
              "rank_prev": 33,
              "rank_prev_patch": 18
            }
          },
          "roles": [
            {
              "name": "FIGHTER",
              "stats": {
                "win_rate": 0.487437,
                "role_rate": 0.938679,
                "play": 199,
                "win": 97
              }
            },
            {
              "name": "TANK",
              "stats": {
                "win_rate": 0.454545,
                "role_rate": 0.0654762,
                "play": 11,
                "win": 5
              }
            },
            {
              "name": "SLAYER",
              "stats": {
                "win_rate": 0.5,
                "role_rate": 0.0185185,
                "play": 2,
                "win": 1
              }
            }
          ],
          "counters": []
        }
      ],
      "roles": []
    },
    "opponents": [
      [],
      []
    ],
    "counters": []
  },
  "summoner_spells": [
    {
      "ids": [
        4,
        11
      ],
      "win": 98,
      "play": 200,
      "pick_rate": 1
    }
  ],
  "trends": {
    "total_rank": 168,
    "total_position_rank": 47,
    "win": [
      {
        "version": "14.19",
        "rate": 0.4903,
        "rank": 29,
        "created_at": "2024-09-24T22:31:28+09:00"
      },
      {
        "version": "14.18",
        "rate": 0.5202,
        "rank": 5,
        "created_at": "2024-09-23T22:31:22+09:00"
      },
      {
        "version": "14.17",
        "rate": 0.5195,
        "rank": 5,
        "created_at": "2024-09-09T22:31:38+09:00"
      },
      {
        "version": "14.16",
        "rate": 0.5179,
        "rank": 6,
        "created_at": "2024-08-26T22:35:51+09:00"
      },
      {
        "version": "14.15",
        "rate": 0.5155,
        "rank": 13,
        "created_at": "2024-08-12T23:36:41+09:00"
      },
      {
        "version": "14.14",
        "rate": 0.5182,
        "rank": 8,
        "created_at": "2024-07-29T23:15:12+09:00"
      },
      {
        "version": "14.13",
        "rate": 0.5133,
        "rank": 13,
        "created_at": "2024-07-15T23:14:12+09:00"
      },
      {
        "version": "14.12",
        "rate": 0.5144,
        "rank": 17,
        "created_at": "2024-06-24T23:11:54+09:00"
      },
      {
        "version": "14.11",
        "rate": 0.5281,
        "rank": 2,
        "created_at": "2024-06-10T23:11:19+09:00"
      },
      {
        "version": "14.10",
        "rate": 0.5337,
        "rank": 1,
        "created_at": "2024-05-28T23:08:43+09:00"
      }
    ],
    "pick": [
      {
        "version": "14.19",
        "rate": 0.0272,
        "rank": 27,
        "created_at": "2024-09-24T22:31:28+09:00"
      },
      {
        "version": "14.18",
        "rate": 0.0168,
        "rank": 38,
        "created_at": "2024-09-23T22:31:22+09:00"
      },
      {
        "version": "14.17",
        "rate": 0.0169,
        "rank": 40,
        "created_at": "2024-09-09T22:31:38+09:00"
      },
      {
        "version": "14.16",
        "rate": 0.017,
        "rank": 37,
        "created_at": "2024-08-26T22:35:51+09:00"
      },
      {
        "version": "14.15",
        "rate": 0.0172,
        "rank": 38,
        "created_at": "2024-08-12T23:36:41+09:00"
      },
      {
        "version": "14.14",
        "rate": 0.0169,
        "rank": 41,
        "created_at": "2024-07-29T23:15:12+09:00"
      },
      {
        "version": "14.13",
        "rate": 0.017,
        "rank": 41,
        "created_at": "2024-07-15T23:14:12+09:00"
      },
      {
        "version": "14.12",
        "rate": 0.022,
        "rank": 36,
        "created_at": "2024-06-24T23:11:54+09:00"
      },
      {
        "version": "14.11",
        "rate": 0.0386,
        "rank": 20,
        "created_at": "2024-06-10T23:11:19+09:00"
      },
      {
        "version": "14.10",
        "rate": 0.041,
        "rank": 18,
        "created_at": "2024-05-28T23:08:43+09:00"
      }
    ],
    "ban": [
      {
        "version": "14.19",
        "rate": 0.0157,
        "rank": 27,
        "created_at": "2024-09-24T22:31:28+09:00"
      },
      {
        "version": "14.18",
        "rate": 0.0101,
        "rank": 38,
        "created_at": "2024-09-23T22:31:22+09:00"
      },
      {
        "version": "14.17",
        "rate": 0.0096,
        "rank": 35,
        "created_at": "2024-09-09T22:31:38+09:00"
      },
      {
        "version": "14.16",
        "rate": 0.0106,
        "rank": 32,
        "created_at": "2024-08-26T22:35:51+09:00"
      },
      {
        "version": "14.15",
        "rate": 0.0104,
        "rank": 33,
        "created_at": "2024-08-12T23:36:41+09:00"
      },
      {
        "version": "14.14",
        "rate": 0.0107,
        "rank": 35,
        "created_at": "2024-07-29T23:15:12+09:00"
      },
      {
        "version": "14.13",
        "rate": 0.0135,
        "rank": 33,
        "created_at": "2024-07-15T23:14:12+09:00"
      },
      {
        "version": "14.12",
        "rate": 0.0224,
        "rank": 26,
        "created_at": "2024-06-24T23:11:54+09:00"
      },
      {
        "version": "14.11",
        "rate": 0.0418,
        "rank": 17,
        "created_at": "2024-06-10T23:11:19+09:00"
      },
      {
        "version": "14.10",
        "rate": 0.0316,
        "rank": 21,
        "created_at": "2024-05-28T23:08:43+09:00"
      }
    ]
  },
  "game_lengths": [
    {
      "game_length": 30,
      "rate": 0.428571,
      "average": 0.5,
      "rank": 38
    },
    {
      "game_length": 25,
      "rate": 0.46875,
      "average": 0.5,
      "rank": 34
    },
    {
      "game_length": 0,
      "rate": 0.5,
      "average": 0.5,
      "rank": 26
    },
    {
      "game_length": 35,
      "rate": 0.6,
      "average": 0.5,
      "rank": 7
    },
    {
      "game_length": 40,
      "rate": 0.666667,
      "average": 0.5,
      "rank": 9
    }
  ],
  "skills": [
    {
      "order": [
        "Q",
        "W",
        "E",
        "Q",
        "Q",
        "R",
        "Q",
        "E",
        "Q",
        "E",
        "R",
        "E",
        "E",
        "W",
        "W"
      ],
      "play": 64,
      "win": 41,
      "pick_rate": 0.8205
    },
    {
      "order": [
        "W",
        "Q",
        "E",
        "Q",
        "Q",
        "R",
        "Q",
        "E",
        "Q",
        "E",
        "R",
        "E",
        "E",
        "W",
        "W"
      ],
      "play": 4,
      "win": 3,
      "pick_rate": 0.0513
    },
    {
      "order": [
        "Q",
        "W",
        "E",
        "Q",
        "Q",
        "R",
        "E",
        "E",
        "E",
        "E",
        "R",
        "Q",
        "Q",
        "W",
        "W"
      ],
      "play": 2,
      "win": 2,
      "pick_rate": 0.0256
    },
    {
      "order": [
        "Q",
        "W",
        "E",
        "Q",
        "Q",
        "E",
        "Q",
        "R",
        "Q",
        "E",
        "R",
        "E",
        "E",
        "W",
        "W"
      ],
      "play": 1,
      "win": 1,
      "pick_rate": 0.0128
    },
    {
      "order": [
        "Q",
        "W",
        "E",
        "Q",
        "E",
        "R",
        "Q",
        "E",
        "Q",
        "E",
        "R",
        "Q",
        "E",
        "W",
        "W"
      ],
      "play": 1,
      "win": 1,
      "pick_rate": 0.0128
    }
  ],
  "skill_masteries": [
    {
      "ids": [
        "Q",
        "E",
        "W"
      ],
      "play": 75,
      "win": 49,
      "pick_rate": 0.9615,
      "builds": [
        {
          "order": [
            "Q",
            "W",
            "E",
            "Q",
            "Q",
            "R",
            "Q",
            "E",
            "Q",
            "E",
            "R",
            "E",
            "E",
            "W",
            "W"
          ],
          "play": 64,
          "win": 41,
          "pick_rate": 0.8533
        },
        {
          "order": [
            "W",
            "Q",
            "E",
            "Q",
            "Q",
            "R",
            "Q",
            "E",
            "Q",
            "E",
            "R",
            "E",
            "E",
            "W",
            "W"
          ],
          "play": 4,
          "win": 3,
          "pick_rate": 0.0533
        },
        {
          "order": [
            "Q",
            "W",
            "E",
            "Q",
            "Q",
            "E",
            "Q",
            "R",
            "Q",
            "E",
            "R",
            "E",
            "E",
            "W",
            "W"
          ],
          "play": 1,
          "win": 1,
          "pick_rate": 0.0133
        },
        {
          "order": [
            "Q",
            "W",
            "Q",
            "E",
            "Q",
            "R",
            "Q",
            "E",
            "Q",
            "E",
            "R",
            "E",
            "E",
            "W",
            "W"
          ],
          "play": 1,
          "win": 1,
          "pick_rate": 0.0133
        },
        {
          "order": [
            "Q",
            "W",
            "E",
            "Q",
            "Q",
            "R",
            "Q",
            "E",
            "E",
            "Q",
            "R",
            "E",
            "E",
            "W",
            "W"
          ],
          "play": 1,
          "win": 0,
          "pick_rate": 0.0133
        }
      ]
    },
    {
      "ids": [
        "E",
        "Q",
        "W"
      ],
      "play": 3,
      "win": 3,
      "pick_rate": 0.0385,
      "builds": [
        {
          "order": [
            "Q",
            "W",
            "E",
            "Q",
            "Q",
            "R",
            "E",
            "E",
            "E",
            "E",
            "R",
            "Q",
            "Q",
            "W",
            "W"
          ],
          "play": 2,
          "win": 2,
          "pick_rate": 0.6667
        },
        {
          "order": [
            "Q",
            "W",
            "E",
            "Q",
            "Q",
            "R",
            "Q",
            "E",
            "E",
            "E",
            "R",
            "E",
            "Q",
            "W",
            "W"
          ],
          "play": 1,
          "win": 1,
          "pick_rate": 0.3333
        }
      ]
    }
  ],
  "skill_evolves": [],
  "runes": [
    {
      "id": 8010,
      "primary_page_id": 8000,
      "primary_rune_ids": [
        8010,
        9111,
        9104,
        8014
      ],
      "secondary_page_id": 8300,
      "secondary_rune_ids": [
        8304,
        8347
      ],
      "stat_mod_ids": [
        5005,
        5008,
        5001
      ],
      "play": 131,
      "win": 61,
      "pick_rate": 0.6583
    },
    {
      "id": 8010,
      "primary_page_id": 8000,
      "primary_rune_ids": [
        8010,
        9111,
        9104,
        8014
      ],
      "secondary_page_id": 8300,
      "secondary_rune_ids": [
        8304,
        8347
      ],
      "stat_mod_ids": [
        5005,
        5008,
        5011
      ],
      "play": 10,
      "win": 3,
      "pick_rate": 0.0503
    },
    {
      "id": 8010,
      "primary_page_id": 8000,
      "primary_rune_ids": [
        8010,
        9111,
        9104,
        8014
      ],
      "secondary_page_id": 8300,
      "secondary_rune_ids": [
        8304,
        8347
      ],
      "stat_mod_ids": [
        5008,
        5008,
        5001
      ],
      "play": 8,
      "win": 3,
      "pick_rate": 0.0402
    },
    {
      "id": 8010,
      "primary_page_id": 8000,
      "primary_rune_ids": [
        8010,
        9111,
        9104,
        8014
      ],
      "secondary_page_id": 8300,
      "secondary_rune_ids": [
        8304,
        8347
      ],
      "stat_mod_ids": [
        5005,
        5008,
        5013
      ],
      "play": 7,
      "win": 3,
      "pick_rate": 0.0352
    },
    {
      "id": 8010,
      "primary_page_id": 8000,
      "primary_rune_ids": [
        8010,
        9111,
        9104,
        8014
      ],
      "secondary_page_id": 8300,
      "secondary_rune_ids": [
        8304,
        8347
      ],
      "stat_mod_ids": [
        5008,
        5008,
        5013
      ],
      "play": 6,
      "win": 3,
      "pick_rate": 0.0302
    }
  ],
  "rune_pages": [
    {
      "id": 8010,
      "primary_page_id": 8000,
      "secondary_page_id": 8300,
      "play": 181,
      "win": 85,
      "pick_rate": 0.9095,
      "builds": [
        {
          "id": 8010,
          "primary_page_id": 8000,
          "primary_rune_ids": [
            8010,
            9111,
            9104,
            8014
          ],
          "secondary_page_id": 8300,
          "secondary_rune_ids": [
            8304,
            8347
          ],
          "stat_mod_ids": [
            5005,
            5008,
            5001
          ],
          "play": 131,
          "win": 61,
          "pick_rate": 0.7238
        },
        {
          "id": 8010,
          "primary_page_id": 8000,
          "primary_rune_ids": [
            8010,
            9111,
            9104,
            8014
          ],
          "secondary_page_id": 8300,
          "secondary_rune_ids": [
            8304,
            8347
          ],
          "stat_mod_ids": [
            5005,
            5008,
            5011
          ],
          "play": 10,
          "win": 3,
          "pick_rate": 0.0552
        },
        {
          "id": 8010,
          "primary_page_id": 8000,
          "primary_rune_ids": [
            8010,
            9111,
            9104,
            8014
          ],
          "secondary_page_id": 8300,
          "secondary_rune_ids": [
            8304,
            8347
          ],
          "stat_mod_ids": [
            5008,
            5008,
            5001
          ],
          "play": 8,
          "win": 3,
          "pick_rate": 0.0442
        },
        {
          "id": 8010,
          "primary_page_id": 8000,
          "primary_rune_ids": [
            8010,
            9111,
            9104,
            8014
          ],
          "secondary_page_id": 8300,
          "secondary_rune_ids": [
            8304,
            8347
          ],
          "stat_mod_ids": [
            5005,
            5008,
            5013
          ],
          "play": 7,
          "win": 3,
          "pick_rate": 0.0387
        },
        {
          "id": 8010,
          "primary_page_id": 8000,
          "primary_rune_ids": [
            8010,
            9111,
            9104,
            8014
          ],
          "secondary_page_id": 8300,
          "secondary_rune_ids": [
            8304,
            8347
          ],
          "stat_mod_ids": [
            5008,
            5008,
            5013
          ],
          "play": 6,
          "win": 3,
          "pick_rate": 0.0331
        }
      ]
    },
    {
      "id": 8010,
      "primary_page_id": 8000,
      "secondary_page_id": 8100,
      "play": 10,
      "win": 7,
      "pick_rate": 0.0503,
      "builds": [
        {
          "id": 8010,
          "primary_page_id": 8000,
          "primary_rune_ids": [
            8010,
            9111,
            9104,
            8014
          ],
          "secondary_page_id": 8100,
          "secondary_rune_ids": [
            8135,
            8138
          ],
          "stat_mod_ids": [
            5005,
            5008,
            5001
          ],
          "play": 4,
          "win": 2,
          "pick_rate": 0.4
        },
        {
          "id": 8010,
          "primary_page_id": 8000,
          "primary_rune_ids": [
            8010,
            9111,
            9104,
            8014
          ],
          "secondary_page_id": 8100,
          "secondary_rune_ids": [
            8135,
            8138
          ],
          "stat_mod_ids": [
            5008,
            5008,
            5013
          ],
          "play": 3,
          "win": 3,
          "pick_rate": 0.3
        },
        {
          "id": 8010,
          "primary_page_id": 8000,
          "primary_rune_ids": [
            8010,
            9111,
            9104,
            8014
          ],
          "secondary_page_id": 8100,
          "secondary_rune_ids": [
            8135,
            8138
          ],
          "stat_mod_ids": [
            5008,
            5008,
            5001
          ],
          "play": 2,
          "win": 2,
          "pick_rate": 0.2
        },
        {
          "id": 8010,
          "primary_page_id": 8000,
          "primary_rune_ids": [
            8010,
            9111,
            9104,
            8014
          ],
          "secondary_page_id": 8100,
          "secondary_rune_ids": [
            8135,
            8143
          ],
          "stat_mod_ids": [
            5005,
            5008,
            5001
          ],
          "play": 1,
          "win": 0,
          "pick_rate": 0.1
        }
      ]
    },
    {
      "id": 8005,
      "primary_page_id": 8000,
      "secondary_page_id": 8300,
      "play": 2,
      "win": 2,
      "pick_rate": 0.0101,
      "builds": [
        {
          "id": 8005,
          "primary_page_id": 8000,
          "primary_rune_ids": [
            8005,
            9111,
            9104,
            8014
          ],
          "secondary_page_id": 8300,
          "secondary_rune_ids": [
            8304,
            8347
          ],
          "stat_mod_ids": [
            5005,
            5008,
            5001
          ],
          "play": 2,
          "win": 2,
          "pick_rate": 1
        }
      ]
    },
    {
      "id": 8010,
      "primary_page_id": 8000,
      "secondary_page_id": 8200,
      "play": 2,
      "win": 1,
      "pick_rate": 0.0101,
      "builds": [
        {
          "id": 8010,
          "primary_page_id": 8000,
          "primary_rune_ids": [
            8010,
            9111,
            9104,
            8014
          ],
          "secondary_page_id": 8200,
          "secondary_rune_ids": [
            8232,
            8275
          ],
          "stat_mod_ids": [
            5008,
            5008,
            5013
          ],
          "play": 1,
          "win": 0,
          "pick_rate": 0.5
        },
        {
          "id": 8010,
          "primary_page_id": 8000,
          "primary_rune_ids": [
            8010,
            9111,
            9104,
            8014
          ],
          "secondary_page_id": 8200,
          "secondary_rune_ids": [
            8224,
            8232
          ],
          "stat_mod_ids": [
            5008,
            5008,
            5001
          ],
          "play": 1,
          "win": 1,
          "pick_rate": 0.5
        }
      ]
    },
    {
      "id": 9923,
      "primary_page_id": 8100,
      "secondary_page_id": 8300,
      "play": 2,
      "win": 1,
      "pick_rate": 0.0101,
      "builds": [
        {
          "id": 9923,
          "primary_page_id": 8100,
          "primary_rune_ids": [
            9923,
            8143,
            8138,
            8135
          ],
          "secondary_page_id": 8300,
          "secondary_rune_ids": [
            8306,
            8347
          ],
          "stat_mod_ids": [
            5008,
            5008,
            5001
          ],
          "play": 1,
          "win": 0,
          "pick_rate": 0.5
        },
        {
          "id": 9923,
          "primary_page_id": 8100,
          "primary_rune_ids": [
            9923,
            8143,
            8138,
            8105
          ],
          "secondary_page_id": 8300,
          "secondary_rune_ids": [
            8304,
            8347
          ],
          "stat_mod_ids": [
            5005,
            5008,
            5001
          ],
          "play": 1,
          "win": 1,
          "pick_rate": 0.5
        }
      ]
    }
  ],
  "core_items": [
    {
      "ids": [
        6631,
        3071,
        3053
      ],
      "play": 41,
      "win": 23,
      "pick_rate": 0.4824
    },
    {
      "ids": [
        6631,
        3161,
        3053
      ],
      "play": 9,
      "win": 6,
      "pick_rate": 0.1059
    },
    {
      "ids": [
        6631,
        3071,
        6333
      ],
      "play": 6,
      "win": 4,
      "pick_rate": 0.0706
    },
    {
      "ids": [
        3748,
        3071,
        3053
      ],
      "play": 2,
      "win": 0,
      "pick_rate": 0.0235
    },
    {
      "ids": [
        6631,
        3071,
        8020
      ],
      "play": 2,
      "win": 2,
      "pick_rate": 0.0235
    },
    {
      "ids": [
        6676,
        6697,
        6701
      ],
      "play": 2,
      "win": 1,
      "pick_rate": 0.0235
    },
    {
      "ids": [
        6631,
        3053,
        6333
      ],
      "play": 1,
      "win": 1,
      "pick_rate": 0.0118
    },
    {
      "ids": [
        6631,
        6609,
        3071
      ],
      "play": 1,
      "win": 1,
      "pick_rate": 0.0118
    },
    {
      "ids": [
        6631,
        3071,
        6695
      ],
      "play": 1,
      "win": 1,
      "pick_rate": 0.0118
    },
    {
      "ids": [
        6631,
        3161,
        3033
      ],
      "play": 1,
      "win": 1,
      "pick_rate": 0.0118
    },
    {
      "ids": [
        3161,
        3748,
        3071
      ],
      "play": 1,
      "win": 1,
      "pick_rate": 0.0118
    },
    {
      "ids": [
        6631,
        3161,
        6673
      ],
      "play": 1,
      "win": 1,
      "pick_rate": 0.0118
    },
    {
      "ids": [
        6631,
        3071,
        6609
      ],
      "play": 1,
      "win": 1,
      "pick_rate": 0.0118
    },
    {
      "ids": [
        6631,
        3161,
        3071
      ],
      "play": 1,
      "win": 1,
      "pick_rate": 0.0118
    },
    {
      "ids": [
        6631,
        3161,
        8020
      ],
      "play": 1,
      "win": 0,
      "pick_rate": 0.0118
    }
  ],
  "boots": [
    {
      "ids": [
        3047
      ],
      "play": 85,
      "win": 39,
      "pick_rate": 0.5313
    },
    {
      "ids": [
        3111
      ],
      "play": 72,
      "win": 37,
      "pick_rate": 0.45
    },
    {
      "ids": [
        3013
      ],
      "play": 1,
      "win": 0,
      "pick_rate": 0.0063
    },
    {
      "ids": [
        3009
      ],
      "play": 1,
      "win": 1,
      "pick_rate": 0.0063
    },
    {
      "ids": [
        3006
      ],
      "play": 1,
      "win": 1,
      "pick_rate": 0.0063
    }
  ],
  "starter_items": [
    {
      "ids": [
        1101,
        2003
      ],
      "play": 127,
      "win": 70,
      "pick_rate": 0.6019
    },
    {
      "ids": [
        1102,
        2003
      ],
      "play": 44,
      "win": 18,
      "pick_rate": 0.2085
    },
    {
      "ids": [
        1101
      ],
      "play": 18,
      "win": 5,
      "pick_rate": 0.0853
    },
    {
      "ids": [
        1103,
        2003
      ],
      "play": 17,
      "win": 10,
      "pick_rate": 0.0806
    },
    {
      "ids": [
        1102
      ],
      "play": 4,
      "win": 0,
      "pick_rate": 0.019
    },
    {
      "ids": [
        1103
      ],
      "play": 1,
      "win": 0,
      "pick_rate": 0.0047
    }
  ],
  "last_items": [
    {
      "ids": [
        6631
      ],
      "play": 191,
      "win": 93,
      "pick_rate": 0.3752
    },
    {
      "ids": [
        3071
      ],
      "play": 115,
      "win": 60,
      "pick_rate": 0.2259
    },
    {
      "ids": [
        3053
      ],
      "play": 63,
      "win": 36,
      "pick_rate": 0.1238
    },
    {
      "ids": [
        3161
      ],
      "play": 25,
      "win": 15,
      "pick_rate": 0.0491
    },
    {
      "ids": [
        6333
      ],
      "play": 12,
      "win": 9,
      "pick_rate": 0.0236
    },
    {
      "ids": [
        6692
      ],
      "play": 10,
      "win": 4,
      "pick_rate": 0.0196
    },
    {
      "ids": [
        3748
      ],
      "play": 9,
      "win": 4,
      "pick_rate": 0.0177
    },
    {
      "ids": [
        3076
      ],
      "play": 8,
      "win": 3,
      "pick_rate": 0.0157
    },
    {
      "ids": [
        3026
      ],
      "play": 8,
      "win": 5,
      "pick_rate": 0.0157
    },
    {
      "ids": [
        3123
      ],
      "play": 6,
      "win": 2,
      "pick_rate": 0.0118
    },
    {
      "ids": [
        3065
      ],
      "play": 6,
      "win": 3,
      "pick_rate": 0.0118
    },
    {
      "ids": [
        3742
      ],
      "play": 6,
      "win": 3,
      "pick_rate": 0.0118
    },
    {
      "ids": [
        8020
      ],
      "play": 5,
      "win": 4,
      "pick_rate": 0.0098
    },
    {
      "ids": [
        3143
      ],
      "play": 5,
      "win": 4,
      "pick_rate": 0.0098
    },
    {
      "ids": [
        6695
      ],
      "play": 5,
      "win": 3,
      "pick_rate": 0.0098
    },
    {
      "ids": [
        6609
      ],
      "play": 4,
      "win": 4,
      "pick_rate": 0.0079
    },
    {
      "ids": [
        3134
      ],
      "play": 3,
      "win": 2,
      "pick_rate": 0.0059
    },
    {
      "ids": [
        1038
      ],
      "play": 3,
      "win": 3,
      "pick_rate": 0.0059
    },
    {
      "ids": [
        3075
      ],
      "play": 2,
      "win": 2,
      "pick_rate": 0.0039
    },
    {
      "ids": [
        6610
      ],
      "play": 2,
      "win": 0,
      "pick_rate": 0.0039
    },
    {
      "ids": [
        3156
      ],
      "play": 2,
      "win": 1,
      "pick_rate": 0.0039
    },
    {
      "ids": [
        6676
      ],
      "play": 2,
      "win": 1,
      "pick_rate": 0.0039
    },
    {
      "ids": [
        6697
      ],
      "play": 2,
      "win": 1,
      "pick_rate": 0.0039
    },
    {
      "ids": [
        6701
      ],
      "play": 2,
      "win": 1,
      "pick_rate": 0.0039
    },
    {
      "ids": [
        3033
      ],
      "play": 2,
      "win": 1,
      "pick_rate": 0.0039
    },
    {
      "ids": [
        3190
      ],
      "play": 1,
      "win": 1,
      "pick_rate": 0.002
    },
    {
      "ids": [
        6665
      ],
      "play": 1,
      "win": 1,
      "pick_rate": 0.002
    },
    {
      "ids": [
        3109
      ],
      "play": 1,
      "win": 1,
      "pick_rate": 0.002
    },
    {
      "ids": [
        3031
      ],
      "play": 1,
      "win": 1,
      "pick_rate": 0.002
    },
    {
      "ids": [
        4401
      ],
      "play": 1,
      "win": 0,
      "pick_rate": 0.002
    }
  ]
}