{
  "summary": {
    "version": {
      "patch_index": 1423,
      "version": "14.23"
    },
    "versions": [
      "14.23",
      "14.22",
      "14.21"
    ],
    "meta": {
      "id": 13,
      "key": "Ryze",
      "name": "符文法师",
      "image_url": "https://opgg-static.akamaized.net/meta/images/lol/latest/champion/Ryze.png",
      "evolve": [],
      "title": "瑞兹",
      "partype": "法力",
      "passive": {
        "name": "奥术专精",
        "description": "<mainText>瑞兹的技能会造成基于他法力值加成的额外伤害，并且他的最大法力值会基于他的法术强度来获得百分比的提升。</mainText>",
        "image_url": "https://opgg-static.akamaized.net/meta/images/lol/latest/passive/Ryze_P.png",
        "video_url": null
      },
      "spells": [
        {
          "key": "Q",
          "name": "超负荷",
          "description": "被动部分：瑞兹的其它基础技能会重置【超负荷】的冷却时间并且充能一层符文。当瑞兹带着2层符文施放【超负荷】时，他会获得短暂的爆发性移动速度加成。<br><br>施放时，瑞兹会沿直线扔出一团纯粹能量，来对命中的第一个敌人造成伤害。如果目标身上有【涌动】效果，那么【超负荷】会造成额外伤害并弹射至附近带有【涌动】效果的敌人身上。",
          "max_rank": 5,
          "range_burn": [
            1000
          ],
          "cooldown_burn": [
            5
          ],
          "cooldown_burn_float": [
            5
          ],
          "cost_burn": [
            40,
            38,
            36,
            34,
            32
          ],
          "tooltip": "<spellPassive>被动：</spellPassive><spellName>符文禁锢</spellName>和<spellName>法术涌动</spellName>会刷新这个技能的冷却时间并充能一枚符文，持续?秒(最多?枚符文)。<br /><br /><spellActive>主动：</spellActive>瑞兹释放一次魔爆，对命中的第一个敌人造成<magicDamage>?魔法伤害</magicDamage>。如果目标带有<keywordMajor>涌动</keywordMajor>，则它会将其消耗，使这个技能造成?%伤害提升并弹射至附近带有<keywordMajor>涌动</keywordMajor>的敌人们。<br /><br />如果?枚符文已被充能，瑞兹就会释放所有符文的能量，来为瑞兹提供持续?秒的<speed>?%移动速度</speed>。<br />?",
          "image_url": "https://opgg-static.akamaized.net/meta/images/lol/latest/spell/RyzeQWrapper.png",
          "video_url": "https://d28xe8vt774jo5.cloudfront.net/champion-abilities/0013/ability_0013_Q1.webm"
        },
        {
          "key": "W",
          "name": "符文禁锢",
          "description": "瑞兹将一个目标陷入一个符文牢笼中，来对其造成伤害和减速效果。如果目标身上带有【涌动】效果，那么减速效果会替换为禁锢效果。",
          "max_rank": 5,
          "range_burn": [
            615
          ],
          "cooldown_burn": [
            11,
            10,
            10,
            9,
            9
          ],
          "cooldown_burn_float": [
            11,
            10.5,
            10,
            9.5,
            9
          ],
          "cost_burn": [
            40,
            55,
            70,
            85,
            100
          ],
          "tooltip": "瑞兹造成<magicDamage>?魔法伤害</magicDamage>和持续?秒的?%<status>减速</status>。如果目标带有<keywordMajor>涌动</keywordMajor>，则它会将其消耗，使这个技能造成<status>禁锢</status>而非<status>减速</status>。?",
          "image_url": "https://opgg-static.akamaized.net/meta/images/lol/latest/spell/RyzeW.png",
          "video_url": "https://d28xe8vt774jo5.cloudfront.net/champion-abilities/0013/ability_0013_W1.webm"
        },
        {
          "key": "E",
          "name": "法术涌动",
          "description": "瑞兹放出一颗纯净魔法能量球，对一名敌人造成伤害并对附近的敌人造成减益效果。瑞兹的技能可以对带有该减益的敌人造成额外效果。",
          "max_rank": 5,
          "range_burn": [
            615
          ],
          "cooldown_burn": [
            3,
            3,
            3,
            2,
            2
          ],
          "cooldown_burn_float": [
            3.5,
            3.25,
            3,
            2.75,
            2.5
          ],
          "cost_burn": [
            35,
            45,
            55,
            65,
            75
          ],
          "tooltip": "瑞兹发射一颗法球，造成<magicDamage>?魔法伤害</magicDamage>并施加持续?秒的<keywordMajor>涌动</keywordMajor>给目标和附近的敌人们。已被<keywordMajor>涌动</keywordMajor>影响的敌人们将使其进一步扩散。?",
          "image_url": "https://opgg-static.akamaized.net/meta/images/lol/latest/spell/RyzeE.png",
          "video_url": "https://d28xe8vt774jo5.cloudfront.net/champion-abilities/0013/ability_0013_E1.webm"
        },
        {
          "key": "R",
          "name": "曲境折跃",
          "description": "被动部分：【超负荷】对带有【涌动】效果的目标造成更多伤害。<br><br>施放时，瑞兹会创造一个传送门来通向一个附近的位置。在若干秒后，站在传送门附近的友军会被传送至目标位置。",
          "max_rank": 3,
          "range_burn": [
            3000
          ],
          "cooldown_burn": [
            180,
            160,
            140
          ],
          "cooldown_burn_float": [
            180,
            160,
            140
          ],
          "cost_burn": [
            100
          ],
          "tooltip": "<spellPassive>被动：</spellPassive> <spellName>超负荷</spellName>对带有<keywordMajor>涌动</keywordMajor>的目标的伤害加成提升至?%。<br /><br /><spellActive>主动：</spellActive>瑞兹开启一个前往另一个位置的传送门。在?秒后，传送门附近的所有友军都会被传送到该位置。?",
          "image_url": "https://opgg-static.akamaized.net/meta/images/lol/latest/spell/RyzeR.png",
          "video_url": "https://d28xe8vt774jo5.cloudfront.net/champion-abilities/0013/ability_0013_R1.webm"
        }
      ],
      "skins": [
        {
          "id": 13000,
          "champion_id": 13,
          "name": "default",
          "centered_image": "https://opgg-static.akamaized.net/meta/images/lol/latest/champion/centered/Ryze_0.jpg",
          "skin_video_url": null,
          "prices": [
            {
              "currency": "IP",
              "cost": 4800
            },
            {
              "currency": "RP",
              "cost": 260
            }
          ],
          "sales": null,
          "release_date": null
        },
        {
          "id": 13010,
          "champion_id": 13,
          "name": "SKT T1 瑞兹",
          "centered_image": "https://opgg-static.akamaized.net/meta/images/lol/latest/champion/centered/Ryze_10.jpg",
          "skin_video_url": null,
          "prices": [
            {
              "currency": "RP",
              "cost": 975
            }
          ],
          "sales": null,
          "release_date": null
        },
        {
          "id": 13011,
          "champion_id": 13,
          "name": "冠军之志 瑞兹",
          "centered_image": "https://opgg-static.akamaized.net/meta/images/lol/latest/champion/centered/Ryze_11.jpg",
          "skin_video_url": null,
          "prices": [
            {
              "currency": "RP",
              "cost": 1350
            }
          ],
          "sales": null,
          "release_date": null
        },
        {
          "id": 13020,
          "champion_id": 13,
          "name": "孤勇之隐 瑞兹",
          "centered_image": "https://opgg-static.akamaized.net/meta/images/lol/latest/champion/centered/Ryze_20.jpg",
          "skin_video_url": "https://youtu.be/Dsf4GX690Xg",
          "prices": [
            {
              "currency": "RP",
              "cost": 1350
            }
          ],
          "sales": null,
          "release_date": "2022-04-14T04:00:00+09:00"
        },
        {
          "id": 13004,
          "champion_id": 13,
          "name": "守护者雕像 瑞兹",
          "centered_image": "https://opgg-static.akamaized.net/meta/images/lol/latest/champion/centered/Ryze_4.jpg",
          "skin_video_url": null,
          "prices": null,
          "sales": null,
          "release_date": null
        },
        {
          "id": 13005,
          "champion_id": 13,
          "name": "宗师级法师训练师 瑞兹",
          "centered_image": "https://opgg-static.akamaized.net/meta/images/lol/latest/champion/centered/Ryze_5.jpg",
          "skin_video_url": null,
          "prices": null,
          "sales": null,
          "release_date": null
        },
        {
          "id": 13007,
          "champion_id": 13,
          "name": "恶魔男爵 瑞兹",
          "centered_image": "https://opgg-static.akamaized.net/meta/images/lol/latest/champion/centered/Ryze_7.jpg",
          "skin_video_url": "https://youtu.be/S2-AOOUTKKA",
          "prices": [
            {
              "currency": "RP",
              "cost": 975
            }
          ],
          "sales": null,
          "release_date": "2012-02-21T08:00:00+09:00"
        },
        {
          "id": 13013,
          "champion_id": 13,
          "name": "沙之守护 瑞兹",
          "centered_image": "https://opgg-static.akamaized.net/meta/images/lol/latest/champion/centered/Ryze_13.jpg",
          "skin_video_url": "https://youtu.be/pdgJY9y-jU4",
          "prices": [
            {
              "currency": "RP",
              "cost": 1350
            }
          ],
          "sales": null,
          "release_date": "2020-01-22T04:00:00+09:00"
        },
        {
          "id": 13008,
          "champion_id": 13,
          "name": "海贼 瑞兹",
          "centered_image": "https://opgg-static.akamaized.net/meta/images/lol/latest/champion/centered/Ryze_8.jpg",
          "skin_video_url": null,
          "prices": [
            {
              "currency": "RP",
              "cost": 975
            }
          ],
          "sales": null,
          "release_date": "2024-10-23T08:59:00+09:00"
        },
        {
          "id": 13009,
          "champion_id": 13,
          "name": "瑞兹·白须",
          "centered_image": "https://opgg-static.akamaized.net/meta/images/lol/latest/champion/centered/Ryze_9.jpg",
          "skin_video_url": "https://youtu.be/Nwn3DcM13jM",
          "prices": [
            {
              "currency": "RP",
              "cost": 750
            }
          ],
          "sales": null,
          "release_date": "2015-12-07T09:00:00+09:00"
        },
        {
          "id": 13003,
          "champion_id": 13,
          "name": "美国大叔 瑞兹",
          "centered_image": "https://opgg-static.akamaized.net/meta/images/lol/latest/champion/centered/Ryze_3.jpg",
          "skin_video_url": "https://youtu.be/W2Sq8mdRkg0",
          "prices": [
            {
              "currency": "RP",
              "cost": 520
            }
          ],
          "sales": null,
          "release_date": "2016-07-10T15:00:00+09:00"
        },
        {
          "id": 13006,
          "champion_id": 13,
          "name": "至死不渝 瑞兹",
          "centered_image": "https://opgg-static.akamaized.net/meta/images/lol/latest/champion/centered/Ryze_6.jpg",
          "skin_video_url": null,
          "prices": [
            {
              "currency": "RP",
              "cost": 975
            }
          ],
          "sales": null,
          "release_date": "2024-10-23T08:59:00+09:00"
        },
        {
          "id": 13002,
          "champion_id": 13,
          "name": "部落精神 瑞兹",
          "centered_image": "https://opgg-static.akamaized.net/meta/images/lol/latest/champion/centered/Ryze_2.jpg",
          "skin_video_url": "https://youtu.be/tqG9RAu5w7s",
          "prices": null,
          "sales": null,
          "release_date": null
        },
        {
          "id": 13001,
          "champion_id": 13,
          "name": "青年 瑞兹",
          "centered_image": "https://opgg-static.akamaized.net/meta/images/lol/latest/champion/centered/Ryze_1.jpg",
          "skin_video_url": null,
          "prices": null,
          "sales": null,
          "release_date": null
        }
      ]
    },
    "summary": {
      "id": 13,
      "is_rotation": false,
      "is_rip": false,
      "average_stats": {
        "play": 1631,
        "win_rate": 0.522379,
        "pick_rate": 0.0465431,
        "ban_rate": 0.00625235,
        "kda": 2.287135,
        "tier": 2,
        "rank": 36,
        "tier_data": {
          "tier": 2,
          "rank": 36,
          "rank_prev": 9,
          "rank_prev_patch": 44
        }
      },
      "positions": [
        {
          "name": "MID",
          "stats": {
            "play": 1113,
            "win_rate": 0.52381,
            "pick_rate": 0.0316981,
            "role_rate": 0.682403,
            "ban_rate": 0.00426663,
            "kda": 2.414195,
            "tier_data": {
              "tier": 2,
              "rank": 10,
              "rank_prev": 8,
              "rank_prev_patch": 12
            }
          },
          "roles": [
            {
              "name": "MAGE",
              "stats": {
                "win_rate": 0.526502,
                "role_rate": 0.98951,
                "play": 1132,
                "win": 596
              }
            }
          ],
          "counters": [
            {
              "champion_id": 777,
              "play": 43,
              "win": 18
            },
            {
              "champion_id": 103,
              "play": 68,
              "win": 34
            },
            {
              "champion_id": 7,
              "play": 34,
              "win": 20
            }
          ]
        },
        {
          "name": "TOP",
          "stats": {
            "play": 507,
            "win_rate": 0.518738,
            "pick_rate": 0.0145125,
            "role_rate": 0.310852,
            "ban_rate": 0.00194356,
            "kda": 2.023377,
            "tier_data": {
              "tier": 3,
              "rank": 36,
              "rank_prev": 25,
              "rank_prev_patch": 37
            }
          },
          "roles": [
            {
              "name": "MAGE",
              "stats": {
                "win_rate": 0.517442,
                "role_rate": 0.984733,
                "play": 516,
                "win": 267
              }
            },
            {
              "name": "TANK",
              "stats": {
                "win_rate": 0.571429,
                "role_rate": 0.0133588,
                "play": 7,
                "win": 4
              }
            }
          ],
          "counters": [
            {
              "champion_id": 799,
              "play": 34,
              "win": 18
            }
          ]
        }
      ],
      "roles": []
    },
    "opponents": [
      [
        {
          "champion_id": 799,
          "play": 34,
          "win": 18,
          "meta": {
            "id": 799,
            "key": "Ambessa",
            "name": "铁血狼母",
            "image_url": "https://opgg-static.akamaized.net/meta/images/lol/latest/champion/Ambessa.png",
            "evolve": [],
            "title": "安蓓萨",
            "partype": "能量",
            "passive": {
              "name": "龙犬诡步",
              "description": "在施放技能的同时输入攻击或移动指令，会使安蓓萨在施放技能后冲刺一小段距离，为她的下一次攻击提供额外的攻击距离、伤害和攻击速度，并返还能量。",
              "image_url": "https://opgg-static.akamaized.net/meta/images/lol/latest/passive/Icon_Ambessa_Passive.Domina.png",
              "video_url": "https://d28xe8vt774jo5.cloudfront.net/champion-abilities/0799/ability_0799_P1.webm"
            },
            "spells": [
              {
                "key": "Q",
                "name": "暗袭 / 裂斩",
                "description": "安蓓萨甩出链刃横扫她前方的半圆区域，对被链刃命中的敌人造成额外伤害。击中一个敌人后，该技能在短时间内的下一次施放会发生变化，使她向前方的一条直线猛砸链刃，对命中的首个敌人造成额外伤害。",
                "max_rank": 5,
                "range_burn": [
                  650
                ],
                "cooldown_burn": [
                  14,
                  13,
                  12,
                  11,
                  10
                ],
                "cooldown_burn_float": [
                  14,
                  13,
                  12,
                  11,
                  10
                ],
                "cost_burn": [
                  70
                ],
                "tooltip": "<spellActive>暗袭</spellActive>：安蓓萨向前甩出链刃，对打击范围边缘区域的敌人们造成<physicalDamage>?+?最大生命值的物理伤害</physicalDamage>。所有其他敌人受到?伤害。击中敌人会让<spellActive>裂斩</spellActive>就绪。<br /><br /><spellActive>裂斩</spellActive>：安蓓萨向下猛砸她的链刃，对首个命中的敌人造成<physicalDamage>?+?最大生命值的物理伤害</physicalDamage>。所有其他敌人受到?伤害。?",
                "image_url": "https://opgg-static.akamaized.net/meta/images/lol/latest/spell/AmbessaQ.png",
                "video_url": "https://d28xe8vt774jo5.cloudfront.net/champion-abilities/0799/ability_0799_Q1.webm"
              },
              {
                "key": "W",
                "name": "铁令",
                "description": "安蓓萨获得一道护盾，在短时间内摆出防守姿势，随后猛砸地面，对附近敌人造成伤害。如果她在防守姿势期间格挡了任何来自非小兵单位的伤害，该技能将造成额外伤害。",
                "max_rank": 5,
                "range_burn": [
                  325
                ],
                "cooldown_burn": [
                  18,
                  17,
                  16,
                  15,
                  14
                ],
                "cooldown_burn_float": [
                  18,
                  17,
                  16,
                  15,
                  14
                ],
                "cost_burn": [
                  70
                ],
                "tooltip": "安蓓萨获得持续?秒的<shield>?护盾值</shield>，并摆出防守姿势?秒。随后猛砸地面，对附近的敌人造成<physicalDamage>?物理伤害</physicalDamage>，如果她成功格挡了来自敌方英雄、大型野怪或建筑物的伤害，则造成的伤害值提升至<physicalDamage>?物理伤害</physicalDamage>。?",
                "image_url": "https://opgg-static.akamaized.net/meta/images/lol/latest/spell/AmbessaW.png",
                "video_url": "https://d28xe8vt774jo5.cloudfront.net/champion-abilities/0799/ability_0799_W1.webm"
              },
              {
                "key": "E",
                "name": "血戮",
                "description": "安蓓萨环绕自身挥舞链刃，对附近的敌人们造成伤害和减速。若在施放该技能后使用【龙犬诡步】，则会在冲刺结束时进行第二次打击。",
                "max_rank": 5,
                "range_burn": [
                  325
                ],
                "cooldown_burn": [
                  13,
                  12,
                  11,
                  10,
                  9
                ],
                "cooldown_burn_float": [
                  13,
                  12,
                  11,
                  10,
                  9
                ],
                "cost_burn": [
                  70
                ],
                "tooltip": "安蓓萨环绕自身挥舞她的链刃，对敌人们造成<physicalDamage>?物理伤害</physicalDamage>和<status>?%</status><status>减速</status>，这个减速效果会在?秒内持续衰减。来自这个技能的第一段<spellName>龙犬诡步</spellName>会触发一次额外打击。?",
                "image_url": "https://opgg-static.akamaized.net/meta/images/lol/latest/spell/AmbessaE.png",
                "video_url": "https://d28xe8vt774jo5.cloudfront.net/champion-abilities/0799/ability_0799_E1.webm"
              },
              {
                "key": "R",
                "name": "公开处刑",
                "description": "安蓓萨选择一条直线，然后瞬移到直线上相距最远的那个敌方英雄身旁，并在到达后压制该英雄。随后将目标砸向地面，对其造成伤害和晕眩。",
                "max_rank": 3,
                "range_burn": [
                  1250
                ],
                "cooldown_burn": [
                  130,
                  115,
                  100
                ],
                "cooldown_burn_float": [
                  130,
                  115,
                  100
                ],
                "cost_burn": [
                  0
                ],
                "tooltip": "<spellPassive>被动：</spellPassive>安蓓萨获得<armorPen>?% %i:scaleAPen%护甲穿透</armorPen>，她的技能会为自身<healing>回复生命值，回复量相当于?的已造成伤害值</healing>。<br /><br /><spellActive>主动</spellActive>：安蓓萨进入<attention>不可阻挡</attention>状态，瞬移到一条直线上距离最远的敌方英雄身旁，<status>压制</status>目标?秒，然后将其砸向地面，对其造成<physicalDamage>?物理伤害</physicalDamage>和?秒<status>晕眩</status>。?",
                "image_url": "https://opgg-static.akamaized.net/meta/images/lol/latest/spell/AmbessaR.png",
                "video_url": "https://d28xe8vt774jo5.cloudfront.net/champion-abilities/0799/ability_0799_R1.webm"
              }
            ],
            "skins": [
              {
                "id": 799000,
                "champion_id": 799,
                "name": "default",
                "centered_image": "https://opgg-static.akamaized.net/meta/images/lol/latest/champion/centered/Ambessa_0.jpg",
                "skin_video_url": null,
                "prices": [
                  {
                    "currency": "IP",
                    "cost": 6300
                  },
                  {
                    "currency": "RP",
                    "cost": 975
                  }
                ],
                "sales": null,
                "release_date": null
              },
              {
                "id": 799001,
                "champion_id": 799,
                "name": "狼神英灵 安蓓萨",
                "centered_image": "https://opgg-static.akamaized.net/meta/images/lol/latest/champion/centered/Ambessa_1.jpg",
                "skin_video_url": "https://youtu.be/x5V46J0ltH0",
                "prices": [
                  {
                    "currency": "RP",
                    "cost": 1820
                  }
                ],
                "sales": null,
                "release_date": "2024-11-06T10:00:00+09:00"
              }
            ]
          },
          "win_rate": 52.94
        }
      ],
      [
        {
          "champion_id": 799,
          "play": 34,
          "win": 18,
          "meta": {
            "id": 799,
            "key": "Ambessa",
            "name": "铁血狼母",
            "image_url": "https://opgg-static.akamaized.net/meta/images/lol/latest/champion/Ambessa.png",
            "evolve": [],
            "title": "安蓓萨",
            "partype": "能量",
            "passive": {
              "name": "龙犬诡步",
              "description": "在施放技能的同时输入攻击或移动指令，会使安蓓萨在施放技能后冲刺一小段距离，为她的下一次攻击提供额外的攻击距离、伤害和攻击速度，并返还能量。",
              "image_url": "https://opgg-static.akamaized.net/meta/images/lol/latest/passive/Icon_Ambessa_Passive.Domina.png",
              "video_url": "https://d28xe8vt774jo5.cloudfront.net/champion-abilities/0799/ability_0799_P1.webm"
            },
            "spells": [
              {
                "key": "Q",
                "name": "暗袭 / 裂斩",
                "description": "安蓓萨甩出链刃横扫她前方的半圆区域，对被链刃命中的敌人造成额外伤害。击中一个敌人后，该技能在短时间内的下一次施放会发生变化，使她向前方的一条直线猛砸链刃，对命中的首个敌人造成额外伤害。",
                "max_rank": 5,
                "range_burn": [
                  650
                ],
                "cooldown_burn": [
                  14,
                  13,
                  12,
                  11,
                  10
                ],
                "cooldown_burn_float": [
                  14,
                  13,
                  12,
                  11,
                  10
                ],
                "cost_burn": [
                  70
                ],
                "tooltip": "<spellActive>暗袭</spellActive>：安蓓萨向前甩出链刃，对打击范围边缘区域的敌人们造成<physicalDamage>?+?最大生命值的物理伤害</physicalDamage>。所有其他敌人受到?伤害。击中敌人会让<spellActive>裂斩</spellActive>就绪。<br /><br /><spellActive>裂斩</spellActive>：安蓓萨向下猛砸她的链刃，对首个命中的敌人造成<physicalDamage>?+?最大生命值的物理伤害</physicalDamage>。所有其他敌人受到?伤害。?",
                "image_url": "https://opgg-static.akamaized.net/meta/images/lol/latest/spell/AmbessaQ.png",
                "video_url": "https://d28xe8vt774jo5.cloudfront.net/champion-abilities/0799/ability_0799_Q1.webm"
              },
              {
                "key": "W",
                "name": "铁令",
                "description": "安蓓萨获得一道护盾，在短时间内摆出防守姿势，随后猛砸地面，对附近敌人造成伤害。如果她在防守姿势期间格挡了任何来自非小兵单位的伤害，该技能将造成额外伤害。",
                "max_rank": 5,
                "range_burn": [
                  325
                ],
                "cooldown_burn": [
                  18,
                  17,
                  16,
                  15,
                  14
                ],
                "cooldown_burn_float": [
                  18,
                  17,
                  16,
                  15,
                  14
                ],
                "cost_burn": [
                  70
                ],
                "tooltip": "安蓓萨获得持续?秒的<shield>?护盾值</shield>，并摆出防守姿势?秒。随后猛砸地面，对附近的敌人造成<physicalDamage>?物理伤害</physicalDamage>，如果她成功格挡了来自敌方英雄、大型野怪或建筑物的伤害，则造成的伤害值提升至<physicalDamage>?物理伤害</physicalDamage>。?",
                "image_url": "https://opgg-static.akamaized.net/meta/images/lol/latest/spell/AmbessaW.png",
                "video_url": "https://d28xe8vt774jo5.cloudfront.net/champion-abilities/0799/ability_0799_W1.webm"
              },
              {
                "key": "E",
                "name": "血戮",
                "description": "安蓓萨环绕自身挥舞链刃，对附近的敌人们造成伤害和减速。若在施放该技能后使用【龙犬诡步】，则会在冲刺结束时进行第二次打击。",
                "max_rank": 5,
                "range_burn": [
                  325
                ],
                "cooldown_burn": [
                  13,
                  12,
                  11,
                  10,
                  9
                ],
                "cooldown_burn_float": [
                  13,
                  12,
                  11,
                  10,
                  9
                ],
                "cost_burn": [
                  70
                ],
                "tooltip": "安蓓萨环绕自身挥舞她的链刃，对敌人们造成<physicalDamage>?物理伤害</physicalDamage>和<status>?%</status><status>减速</status>，这个减速效果会在?秒内持续衰减。来自这个技能的第一段<spellName>龙犬诡步</spellName>会触发一次额外打击。?",
                "image_url": "https://opgg-static.akamaized.net/meta/images/lol/latest/spell/AmbessaE.png",
                "video_url": "https://d28xe8vt774jo5.cloudfront.net/champion-abilities/0799/ability_0799_E1.webm"
              },
              {
                "key": "R",
                "name": "公开处刑",
                "description": "安蓓萨选择一条直线，然后瞬移到直线上相距最远的那个敌方英雄身旁，并在到达后压制该英雄。随后将目标砸向地面，对其造成伤害和晕眩。",
                "max_rank": 3,
                "range_burn": [
                  1250
                ],
                "cooldown_burn": [
                  130,
                  115,
                  100
                ],
                "cooldown_burn_float": [
                  130,
                  115,
                  100
                ],
                "cost_burn": [
                  0
                ],
                "tooltip": "<spellPassive>被动：</spellPassive>安蓓萨获得<armorPen>?% %i:scaleAPen%护甲穿透</armorPen>，她的技能会为自身<healing>回复生命值，回复量相当于?的已造成伤害值</healing>。<br /><br /><spellActive>主动</spellActive>：安蓓萨进入<attention>不可阻挡</attention>状态，瞬移到一条直线上距离最远的敌方英雄身旁，<status>压制</status>目标?秒，然后将其砸向地面，对其造成<physicalDamage>?物理伤害</physicalDamage>和?秒<status>晕眩</status>。?",
                "image_url": "https://opgg-static.akamaized.net/meta/images/lol/latest/spell/AmbessaR.png",
                "video_url": "https://d28xe8vt774jo5.cloudfront.net/champion-abilities/0799/ability_0799_R1.webm"
              }
            ],
            "skins": [
              {
                "id": 799000,
                "champion_id": 799,
                "name": "default",
                "centered_image": "https://opgg-static.akamaized.net/meta/images/lol/latest/champion/centered/Ambessa_0.jpg",
                "skin_video_url": null,
                "prices": [
                  {
                    "currency": "IP",
                    "cost": 6300
                  },
                  {
                    "currency": "RP",
                    "cost": 975
                  }
                ],
                "sales": null,
                "release_date": null
              },
              {
                "id": 799001,
                "champion_id": 799,
                "name": "狼神英灵 安蓓萨",
                "centered_image": "https://opgg-static.akamaized.net/meta/images/lol/latest/champion/centered/Ambessa_1.jpg",
                "skin_video_url": "https://youtu.be/x5V46J0ltH0",
                "prices": [
                  {
                    "currency": "RP",
                    "cost": 1820
                  }
                ],
                "sales": null,
                "release_date": "2024-11-06T10:00:00+09:00"
              }
            ]
          },
          "win_rate": 52.94
        }
      ]
    ],
    "counters": [
      {
        "champion_id": 799,
        "play": 34,
        "win": 18,
        "meta": {
          "id": 799,
          "key": "Ambessa",
          "name": "铁血狼母",
          "image_url": "https://opgg-static.akamaized.net/meta/images/lol/latest/champion/Ambessa.png",
          "evolve": [],
          "title": "安蓓萨",
          "partype": "能量",
          "passive": {
            "name": "龙犬诡步",
            "description": "在施放技能的同时输入攻击或移动指令，会使安蓓萨在施放技能后冲刺一小段距离，为她的下一次攻击提供额外的攻击距离、伤害和攻击速度，并返还能量。",
            "image_url": "https://opgg-static.akamaized.net/meta/images/lol/latest/passive/Icon_Ambessa_Passive.Domina.png",
            "video_url": "https://d28xe8vt774jo5.cloudfront.net/champion-abilities/0799/ability_0799_P1.webm"
          },
          "spells": [
            {
              "key": "Q",
              "name": "暗袭 / 裂斩",
              "description": "安蓓萨甩出链刃横扫她前方的半圆区域，对被链刃命中的敌人造成额外伤害。击中一个敌人后，该技能在短时间内的下一次施放会发生变化，使她向前方的一条直线猛砸链刃，对命中的首个敌人造成额外伤害。",
              "max_rank": 5,
              "range_burn": [
                650
              ],
              "cooldown_burn": [
                14,
                13,
                12,
                11,
                10
              ],
              "cooldown_burn_float": [
                14,
                13,
                12,
                11,
                10
              ],
              "cost_burn": [
                70
              ],
              "tooltip": "<spellActive>暗袭</spellActive>：安蓓萨向前甩出链刃，对打击范围边缘区域的敌人们造成<physicalDamage>?+?最大生命值的物理伤害</physicalDamage>。所有其他敌人受到?伤害。击中敌人会让<spellActive>裂斩</spellActive>就绪。<br /><br /><spellActive>裂斩</spellActive>：安蓓萨向下猛砸她的链刃，对首个命中的敌人造成<physicalDamage>?+?最大生命值的物理伤害</physicalDamage>。所有其他敌人受到?伤害。?",
              "image_url": "https://opgg-static.akamaized.net/meta/images/lol/latest/spell/AmbessaQ.png",
              "video_url": "https://d28xe8vt774jo5.cloudfront.net/champion-abilities/0799/ability_0799_Q1.webm"
            },
            {
              "key": "W",
              "name": "铁令",
              "description": "安蓓萨获得一道护盾，在短时间内摆出防守姿势，随后猛砸地面，对附近敌人造成伤害。如果她在防守姿势期间格挡了任何来自非小兵单位的伤害，该技能将造成额外伤害。",
              "max_rank": 5,
              "range_burn": [
                325
              ],
              "cooldown_burn": [
                18,
                17,
                16,
                15,
                14
              ],
              "cooldown_burn_float": [
                18,
                17,
                16,
                15,
                14
              ],
              "cost_burn": [
                70
              ],
              "tooltip": "安蓓萨获得持续?秒的<shield>?护盾值</shield>，并摆出防守姿势?秒。随后猛砸地面，对附近的敌人造成<physicalDamage>?物理伤害</physicalDamage>，如果她成功格挡了来自敌方英雄、大型野怪或建筑物的伤害，则造成的伤害值提升至<physicalDamage>?物理伤害</physicalDamage>。?",
              "image_url": "https://opgg-static.akamaized.net/meta/images/lol/latest/spell/AmbessaW.png",
              "video_url": "https://d28xe8vt774jo5.cloudfront.net/champion-abilities/0799/ability_0799_W1.webm"
            },
            {
              "key": "E",
              "name": "血戮",
              "description": "安蓓萨环绕自身挥舞链刃，对附近的敌人们造成伤害和减速。若在施放该技能后使用【龙犬诡步】，则会在冲刺结束时进行第二次打击。",
              "max_rank": 5,
              "range_burn": [
                325
              ],
              "cooldown_burn": [
                13,
                12,
                11,
                10,
                9
              ],
              "cooldown_burn_float": [
                13,
                12,
                11,
                10,
                9
              ],
              "cost_burn": [
                70
              ],
              "tooltip": "安蓓萨环绕自身挥舞她的链刃，对敌人们造成<physicalDamage>?物理伤害</physicalDamage>和<status>?%</status><status>减速</status>，这个减速效果会在?秒内持续衰减。来自这个技能的第一段<spellName>龙犬诡步</spellName>会触发一次额外打击。?",
              "image_url": "https://opgg-static.akamaized.net/meta/images/lol/latest/spell/AmbessaE.png",
              "video_url": "https://d28xe8vt774jo5.cloudfront.net/champion-abilities/0799/ability_0799_E1.webm"
            },
            {
              "key": "R",
              "name": "公开处刑",
              "description": "安蓓萨选择一条直线，然后瞬移到直线上相距最远的那个敌方英雄身旁，并在到达后压制该英雄。随后将目标砸向地面，对其造成伤害和晕眩。",
              "max_rank": 3,
              "range_burn": [
                1250
              ],
              "cooldown_burn": [
                130,
                115,
                100
              ],
              "cooldown_burn_float": [
                130,
                115,
                100
              ],
              "cost_burn": [
                0
              ],
              "tooltip": "<spellPassive>被动：</spellPassive>安蓓萨获得<armorPen>?% %i:scaleAPen%护甲穿透</armorPen>，她的技能会为自身<healing>回复生命值，回复量相当于?的已造成伤害值</healing>。<br /><br /><spellActive>主动</spellActive>：安蓓萨进入<attention>不可阻挡</attention>状态，瞬移到一条直线上距离最远的敌方英雄身旁，<status>压制</status>目标?秒，然后将其砸向地面，对其造成<physicalDamage>?物理伤害</physicalDamage>和?秒<status>晕眩</status>。?",
              "image_url": "https://opgg-static.akamaized.net/meta/images/lol/latest/spell/AmbessaR.png",
              "video_url": "https://d28xe8vt774jo5.cloudfront.net/champion-abilities/0799/ability_0799_R1.webm"
            }
          ],
          "skins": [
            {
              "id": 799000,
              "champion_id": 799,
              "name": "default",
              "centered_image": "https://opgg-static.akamaized.net/meta/images/lol/latest/champion/centered/Ambessa_0.jpg",
              "skin_video_url": null,
              "prices": [
                {
                  "currency": "IP",
                  "cost": 6300
                },
                {
                  "currency": "RP",
                  "cost": 975
                }
              ],
              "sales": null,
              "release_date": null
            },
            {
              "id": 799001,
              "champion_id": 799,
              "name": "狼神英灵 安蓓萨",
              "centered_image": "https://opgg-static.akamaized.net/meta/images/lol/latest/champion/centered/Ambessa_1.jpg",
              "skin_video_url": "https://youtu.be/x5V46J0ltH0",
              "prices": [
                {
                  "currency": "RP",
                  "cost": 1820
                }
              ],
              "sales": null,
              "release_date": "2024-11-06T10:00:00+09:00"
            }
          ]
        }
      }
    ]
  },
  "summoner_spells": [
    {
      "ids": [
        4,
        12
      ],
      "win": 259,
      "play": 499,
      "pick_rate": 0.994
    },
    {
      "ids": [
        4,
        14
      ],
      "win": 1,
      "play": 1,
      "pick_rate": 0.002
    },
    {
      "ids": [
        4,
        6
      ],
      "win": 1,
      "play": 1,
      "pick_rate": 0.002
    },
    {
      "ids": [
        6,
        12
      ],
      "win": 1,
      "play": 1,
      "pick_rate": 0.002
    }
  ],
  "trends": {
    "total_rank": 169,
    "total_position_rank": 61,
    "win": [
      {
        "version": "14.23",
        "rate": 0.5187,
        "rank": 15,
        "created_at": "2024-11-19T23:02:04+09:00"
      },
      {
        "version": "14.22",
        "rate": 0.5196,
        "rank": 8,
        "created_at": "2024-11-18T22:31:32+09:00"
      },
      {
        "version": "14.21",
        "rate": 0.5256,
        "rank": 3,
        "created_at": "2024-11-04T22:32:41+09:00"
      },
      {
        "version": "14.20",
        "rate": 0.5115,
        "rank": 18,
        "created_at": "2024-10-21T22:29:59+09:00"
      },
      {
        "version": "14.19",
        "rate": 0.5176,
        "rank": 13,
        "created_at": "2024-10-07T22:36:39+09:00"
      },
      {
        "version": "14.18",
        "rate": 0.5163,
        "rank": 15,
        "created_at": "2024-09-23T22:31:22+09:00"
      },
      {
        "version": "14.17",
        "rate": 0.5171,
        "rank": 10,
        "created_at": "2024-09-09T22:31:38+09:00"
      },
      {
        "version": "14.16",
        "rate": 0.5057,
        "rank": 36,
        "created_at": "2024-08-26T22:35:51+09:00"
      },
      {
        "version": "14.15",
        "rate": 0.5028,
        "rank": 40,
        "created_at": "2024-08-12T23:36:41+09:00"
      },
      {
        "version": "14.14",
        "rate": 0.5078,
        "rank": 37,
        "created_at": "2024-07-29T23:15:12+09:00"
      }
    ],
    "pick": [
      {
        "version": "14.23",
        "rate": 0.0145,
        "rank": 50,
        "created_at": "2024-11-19T23:02:04+09:00"
      },
      {
        "version": "14.22",
        "rate": 0.0124,
        "rank": 53,
        "created_at": "2024-11-18T22:31:32+09:00"
      },
      {
        "version": "14.21",
        "rate": 0.0141,
        "rank": 49,
        "created_at": "2024-11-04T22:32:41+09:00"
      },
      {
        "version": "14.20",
        "rate": 0.0101,
        "rank": 52,
        "created_at": "2024-10-21T22:29:59+09:00"
      },
      {
        "version": "14.19",
        "rate": 0.01,
        "rank": 53,
        "created_at": "2024-10-07T22:36:39+09:00"
      },
      {
        "version": "14.18",
        "rate": 0.011,
        "rank": 51,
        "created_at": "2024-09-23T22:31:22+09:00"
      },
      {
        "version": "14.17",
        "rate": 0.0108,
        "rank": 53,
        "created_at": "2024-09-09T22:31:38+09:00"
      },
      {
        "version": "14.16",
        "rate": 0.0056,
        "rank": 57,
        "created_at": "2024-08-26T22:35:51+09:00"
      },
      {
        "version": "14.15",
        "rate": 0.0054,
        "rank": 59,
        "created_at": "2024-08-12T23:36:41+09:00"
      },
      {
        "version": "14.14",
        "rate": 0.0054,
        "rank": 62,
        "created_at": "2024-07-29T23:15:12+09:00"
      }
    ],
    "ban": [
      {
        "version": "14.23",
        "rate": 0.0019,
        "rank": 59,
        "created_at": "2024-11-19T23:02:04+09:00"
      },
      {
        "version": "14.22",
        "rate": 0.0015,
        "rank": 59,
        "created_at": "2024-11-18T22:31:32+09:00"
      },
      {
        "version": "14.21",
        "rate": 0.0016,
        "rank": 57,
        "created_at": "2024-11-04T22:32:41+09:00"
      },
      {
        "version": "14.20",
        "rate": 0.0009,
        "rank": 57,
        "created_at": "2024-10-21T22:29:59+09:00"
      },
      {
        "version": "14.19",
        "rate": 0.0013,
        "rank": 57,
        "created_at": "2024-10-07T22:36:39+09:00"
      },
      {
        "version": "14.18",
        "rate": 0.0012,
        "rank": 56,
        "created_at": "2024-09-23T22:31:22+09:00"
      },
      {
        "version": "14.17",
        "rate": 0.0011,
        "rank": 56,
        "created_at": "2024-09-09T22:31:38+09:00"
      },
      {
        "version": "14.16",
        "rate": 0.0004,
        "rank": 58,
        "created_at": "2024-08-26T22:35:51+09:00"
      },
      {
        "version": "14.15",
        "rate": 0.0004,
        "rank": 59,
        "created_at": "2024-08-12T23:36:41+09:00"
      },
      {
        "version": "14.14",
        "rate": 0.0004,
        "rank": 62,
        "created_at": "2024-07-29T23:15:12+09:00"
      }
    ]
  },
  "game_lengths": [
    {
      "game_length": 25,
      "rate": 0.49711,
      "average": 0.5,
      "rank": 33
    },
    {
      "game_length": 35,
      "rate": 0.511111,
      "average": 0.5,
      "rank": 29
    },
    {
      "game_length": 30,
      "rate": 0.516393,
      "average": 0.5,
      "rank": 26
    },
    {
      "game_length": 0,
      "rate": 0.543046,
      "average": 0.5,
      "rank": 8
    },
    {
      "game_length": 40,
      "rate": 0.5625,
      "average": 0.5,
      "rank": 17
    }
  ],
  "skills": [
    {
      "order": [
        "W",
        "E",
        "Q",
        "Q",
        "Q",
        "R",
        "Q",
        "E",
        "Q",
        "E",
        "R",
        "E",
        "E",
        "W",
        "W"
      ],
      "play": 220,
      "win": 126,
      "pick_rate": 0.5805
    },
    {
      "order": [
        "W",
        "Q",
        "E",
        "Q",
        "Q",
        "R",
        "Q",
        "E",
        "Q",
        "E",
        "R",
        "E",
        "E",
        "W",
        "W"
      ],
      "play": 61,
      "win": 30,
      "pick_rate": 0.1609
    },
    {
      "order": [
        "E",
        "Q",
        "W",
        "Q",
        "Q",
        "R",
        "Q",
        "E",
        "Q",
        "E",
        "R",
        "E",
        "E",
        "W",
        "W"
      ],
      "play": 41,
      "win": 26,
      "pick_rate": 0.1082
    },
    {
      "order": [
        "E",
        "W",
        "Q",
        "Q",
        "Q",
        "R",
        "Q",
        "E",
        "Q",
        "E",
        "R",
        "E",
        "E",
        "W",
        "W"
      ],
      "play": 11,
      "win": 9,
      "pick_rate": 0.029
    },
    {
      "order": [
        "Q",
        "E",
        "W",
        "Q",
        "Q",
        "R",
        "Q",
        "E",
        "Q",
        "E",
        "R",
        "E",
        "E",
        "W",
        "W"
      ],
      "play": 8,
      "win": 5,
      "pick_rate": 0.0211
    }
  ],
  "skill_masteries": [
    {
      "ids": [
        "Q",
        "E",
        "W"
      ],
      "play": 372,
      "win": 215,
      "pick_rate": 0.9815,
      "builds": [
        {
          "order": [
            "W",
            "E",
            "Q",
            "Q",
            "Q",
            "R",
            "Q",
            "E",
            "Q",
            "E",
            "R",
            "E",
            "E",
            "W",
            "W"
          ],
          "play": 220,
          "win": 126,
          "pick_rate": 0.5914
        },
        {
          "order": [
            "W",
            "Q",
            "E",
            "Q",
            "Q",
            "R",
            "Q",
            "E",
            "Q",
            "E",
            "R",
            "E",
            "E",
            "W",
            "W"
          ],
          "play": 61,
          "win": 30,
          "pick_rate": 0.164
        },
        {
          "order": [
            "E",
            "Q",
            "W",
            "Q",
            "Q",
            "R",
            "Q",
            "E",
            "Q",
            "E",
            "R",
            "E",
            "E",
            "W",
            "W"
          ],
          "play": 41,
          "win": 26,
          "pick_rate": 0.1102
        },
        {
          "order": [
            "E",
            "W",
            "Q",
            "Q",
            "Q",
            "R",
            "Q",
            "E",
            "Q",
            "E",
            "R",
            "E",
            "E",
            "W",
            "W"
          ],
          "play": 11,
          "win": 9,
          "pick_rate": 0.0296
        },
        {
          "order": [
            "Q",
            "E",
            "W",
            "Q",
            "Q",
            "R",
            "Q",
            "E",
            "Q",
            "E",
            "R",
            "E",
            "E",
            "W",
            "W"
          ],
          "play": 8,
          "win": 5,
          "pick_rate": 0.0215
        }
      ]
    },
    {
      "ids": [
        "Q",
        "W",
        "E"
      ],
      "play": 5,
      "win": 4,
      "pick_rate": 0.0132,
      "builds": [
        {
          "order": [
            "W",
            "Q",
            "E",
            "Q",
            "Q",
            "R",
            "Q",
            "W",
            "Q",
            "W",
            "R",
            "W",
            "W",
            "E",
            "E"
          ],
          "play": 1,
          "win": 1,
          "pick_rate": 0.2
        },
        {
          "order": [
            "W",
            "Q",
            "E",
            "Q",
            "Q",
            "R",
            "Q",
            "W",
            "Q",
            "W",
            "R",
            "E",
            "E",
            "E",
            "W"
          ],
          "play": 1,
          "win": 1,
          "pick_rate": 0.2
        },
        {
          "order": [
            "W",
            "E",
            "Q",
            "Q",
            "Q",
            "R",
            "Q",
            "W",
            "W",
            "Q",
            "R",
            "W",
            "W",
            "E",
            "E"
          ],
          "play": 1,
          "win": 1,
          "pick_rate": 0.2
        },
        {
          "order": [
            "W",
            "E",
            "Q",
            "W",
            "Q",
            "R",
            "Q",
            "W",
            "Q",
            "Q",
            "R",
            "E",
            "W",
            "W",
            "E"
          ],
          "play": 1,
          "win": 1,
          "pick_rate": 0.2
        },
        {
          "order": [
            "Q",
            "E",
            "W",
            "Q",
            "Q",
            "R",
            "Q",
            "W",
            "Q",
            "W",
            "R",
            "E",
            "W",
            "W",
            "E"
          ],
          "play": 1,
          "win": 0,
          "pick_rate": 0.2
        }
      ]
    },
    {
      "ids": [
        "E",
        "W",
        "Q"
      ],
      "play": 1,
      "win": 1,
      "pick_rate": 0.0026,
      "builds": [
        {
          "order": [
            "W",
            "E",
            "Q",
            "Q",
            "E",
            "R",
            "Q",
            "Q",
            "W",
            "E",
            "R",
            "E",
            "E",
            "W",
            "W"
          ],
          "play": 1,
          "win": 1,
          "pick_rate": 1
        }
      ]
    },
    {
      "ids": [
        "E",
        "Q",
        "W"
      ],
      "play": 1,
      "win": 0,
      "pick_rate": 0.0026,
      "builds": [
        {
          "order": [
            "E",
            "Q",
            "W",
            "Q",
            "Q",
            "R",
            "E",
            "E",
            "E",
            "E",
            "R",
            "Q",
            "Q",
            "W",
            "W"
          ],
          "play": 1,
          "win": 0,
          "pick_rate": 1
        }
      ]
    }
  ],
  "skill_evolves": [],
  "runes": [
    {
      "id": 8230,
      "primary_page_id": 8200,
      "primary_rune_ids": [
        8230,
        8226,
        8210,
        8236
      ],
      "secondary_page_id": 8400,
      "secondary_rune_ids": [
        8451,
        8473
      ],
      "stat_mod_ids": [
        5005,
        5008,
        5001
      ],
      "play": 152,
      "win": 78,
      "pick_rate": 0.3028
    },
    {
      "id": 8230,
      "primary_page_id": 8200,
      "primary_rune_ids": [
        8230,
        8226,
        8210,
        8237
      ],
      "secondary_page_id": 8300,
      "secondary_rune_ids": [
        8345,
        8347
      ],
      "stat_mod_ids": [
        5005,
        5008,
        5001
      ],
      "play": 38,
      "win": 20,
      "pick_rate": 0.0757
    },
    {
      "id": 8010,
      "primary_page_id": 8000,
      "primary_rune_ids": [
        8010,
        8009,
        9105,
        8299
      ],
      "secondary_page_id": 8200,
      "secondary_rune_ids": [
        8210,
        8226
      ],
      "stat_mod_ids": [
        5005,
        5008,
        5001
      ],
      "play": 14,
      "win": 4,
      "pick_rate": 0.0279
    },
    {
      "id": 8230,
      "primary_page_id": 8200,
      "primary_rune_ids": [
        8230,
        8226,
        8210,
        8237
      ],
      "secondary_page_id": 8400,
      "secondary_rune_ids": [
        8451,
        8473
      ],
      "stat_mod_ids": [
        5005,
        5008,
        5011
      ],
      "play": 14,
      "win": 11,
      "pick_rate": 0.0279
    },
    {
      "id": 8230,
      "primary_page_id": 8200,
      "primary_rune_ids": [
        8230,
        8226,
        8210,
        8237
      ],
      "secondary_page_id": 8000,
      "secondary_rune_ids": [
        8009,
        8017
      ],
      "stat_mod_ids": [
        5005,
        5008,
        5011
      ],
      "play": 13,
      "win": 6,
      "pick_rate": 0.0259
    }
  ],
  "rune_pages": [
    {
      "id": 8230,
      "primary_page_id": 8200,
      "secondary_page_id": 8400,
      "play": 245,
      "win": 136,
      "pick_rate": 0.488,
      "builds": [
        {
          "id": 8230,
          "primary_page_id": 8200,
          "primary_rune_ids": [
            8230,
            8226,
            8210,
            8236
          ],
          "secondary_page_id": 8400,
          "secondary_rune_ids": [
            8451,
            8473
          ],
          "stat_mod_ids": [
            5005,
            5008,
            5001
          ],
          "play": 152,
          "win": 78,
          "pick_rate": 0.6204
        },
        {
          "id": 8230,
          "primary_page_id": 8200,
          "primary_rune_ids": [
            8230,
            8226,
            8210,
            8237
          ],
          "secondary_page_id": 8400,
          "secondary_rune_ids": [
            8451,
            8473
          ],
          "stat_mod_ids": [
            5005,
            5008,
            5011
          ],
          "play": 14,
          "win": 11,
          "pick_rate": 0.0571
        },
        {
          "id": 8230,
          "primary_page_id": 8200,
          "primary_rune_ids": [
            8230,
            8226,
            8210,
            8236
          ],
          "secondary_page_id": 8400,
          "secondary_rune_ids": [
            8444,
            8451
          ],
          "stat_mod_ids": [
            5005,
            5008,
            5001
          ],
          "play": 11,
          "win": 8,
          "pick_rate": 0.0449
        },
        {
          "id": 8230,
          "primary_page_id": 8200,
          "primary_rune_ids": [
            8230,
            8226,
            8210,
            8237
          ],
          "secondary_page_id": 8400,
          "secondary_rune_ids": [
            8451,
            8473
          ],
          "stat_mod_ids": [
            5005,
            5008,
            5001
          ],
          "play": 11,
          "win": 6,
          "pick_rate": 0.0449
        },
        {
          "id": 8230,
          "primary_page_id": 8200,
          "primary_rune_ids": [
            8230,
            8226,
            8210,
            8236
          ],
          "secondary_page_id": 8400,
          "secondary_rune_ids": [
            8451,
            8473
          ],
          "stat_mod_ids": [
            5005,
            5008,
            5011
          ],
          "play": 9,
          "win": 6,
          "pick_rate": 0.0367
        }
      ]
    },
    {
      "id": 8230,
      "primary_page_id": 8200,
      "secondary_page_id": 8300,
      "play": 92,
      "win": 41,
      "pick_rate": 0.1833,
      "builds": [
        {
          "id": 8230,
          "primary_page_id": 8200,
          "primary_rune_ids": [
            8230,
            8226,
            8210,
            8237
          ],
          "secondary_page_id": 8300,
          "secondary_rune_ids": [
            8345,
            8347
          ],
          "stat_mod_ids": [
            5005,
            5008,
            5001
          ],
          "play": 38,
          "win": 20,
          "pick_rate": 0.413
        },
        {
          "id": 8230,
          "primary_page_id": 8200,
          "primary_rune_ids": [
            8230,
            8226,
            8210,
            8236
          ],
          "secondary_page_id": 8300,
          "secondary_rune_ids": [
            8345,
            8347
          ],
          "stat_mod_ids": [
            5005,
            5008,
            5001
          ],
          "play": 8,
          "win": 4,
          "pick_rate": 0.087
        },
        {
          "id": 8230,
          "primary_page_id": 8200,
          "primary_rune_ids": [
            8230,
            8226,
            8210,
            8236
          ],
          "secondary_page_id": 8300,
          "secondary_rune_ids": [
            8345,
            8347
          ],
          "stat_mod_ids": [
            5008,
            5008,
            5001
          ],
          "play": 7,
          "win": 4,
          "pick_rate": 0.0761
        },
        {
          "id": 8230,
          "primary_page_id": 8200,
          "primary_rune_ids": [
            8230,
            8226,
            8210,
            8232
          ],
          "secondary_page_id": 8300,
          "secondary_rune_ids": [
            8345,
            8347
          ],
          "stat_mod_ids": [
            5005,
            5008,
            5001
          ],
          "play": 6,
          "win": 2,
          "pick_rate": 0.0652
        },
        {
          "id": 8230,
          "primary_page_id": 8200,
          "primary_rune_ids": [
            8230,
            8226,
            8210,
            8237
          ],
          "secondary_page_id": 8300,
          "secondary_rune_ids": [
            8345,
            8347
          ],
          "stat_mod_ids": [
            5005,
            5008,
            5011
          ],
          "play": 5,
          "win": 0,
          "pick_rate": 0.0543
        }
      ]
    },
    {
      "id": 8230,
      "primary_page_id": 8200,
      "secondary_page_id": 8000,
      "play": 81,
      "win": 46,
      "pick_rate": 0.1614,
      "builds": [
        {
          "id": 8230,
          "primary_page_id": 8200,
          "primary_rune_ids": [
            8230,
            8226,
            8210,
            8237
          ],
          "secondary_page_id": 8000,
          "secondary_rune_ids": [
            8009,
            8017
          ],
          "stat_mod_ids": [
            5005,
            5008,
            5011
          ],
          "play": 13,
          "win": 6,
          "pick_rate": 0.1605
        },
        {
          "id": 8230,
          "primary_page_id": 8200,
          "primary_rune_ids": [
            8230,
            8226,
            8210,
            8237
          ],
          "secondary_page_id": 8000,
          "secondary_rune_ids": [
            8017,
            9105
          ],
          "stat_mod_ids": [
            5005,
            5008,
            5011
          ],
          "play": 9,
          "win": 6,
          "pick_rate": 0.1111
        },
        {
          "id": 8230,
          "primary_page_id": 8200,
          "primary_rune_ids": [
            8230,
            8226,
            8234,
            8237
          ],
          "secondary_page_id": 8000,
          "secondary_rune_ids": [
            8009,
            8017
          ],
          "stat_mod_ids": [
            5005,
            5008,
            5001
          ],
          "play": 7,
          "win": 5,
          "pick_rate": 0.0864
        },
        {
          "id": 8230,
          "primary_page_id": 8200,
          "primary_rune_ids": [
            8230,
            8226,
            8210,
            8237
          ],
          "secondary_page_id": 8000,
          "secondary_rune_ids": [
            9101,
            9105
          ],
          "stat_mod_ids": [
            5008,
            5008,
            5011
          ],
          "play": 6,
          "win": 3,
          "pick_rate": 0.0741
        },
        {
          "id": 8230,
          "primary_page_id": 8200,
          "primary_rune_ids": [
            8230,
            8226,
            8210,
            8237
          ],
          "secondary_page_id": 8000,
          "secondary_rune_ids": [
            8009,
            8017
          ],
          "stat_mod_ids": [
            5005,
            5008,
            5001
          ],
          "play": 6,
          "win": 3,
          "pick_rate": 0.0741
        }
      ]
    },
    {
      "id": 8010,
      "primary_page_id": 8000,
      "secondary_page_id": 8200,
      "play": 33,
      "win": 15,
      "pick_rate": 0.0657,
      "builds": [
        {
          "id": 8010,
          "primary_page_id": 8000,
          "primary_rune_ids": [
            8010,
            8009,
            9105,
            8299
          ],
          "secondary_page_id": 8200,
          "secondary_rune_ids": [
            8210,
            8226
          ],
          "stat_mod_ids": [
            5005,
            5008,
            5001
          ],
          "play": 14,
          "win": 4,
          "pick_rate": 0.4242
        },
        {
          "id": 8010,
          "primary_page_id": 8000,
          "primary_rune_ids": [
            8010,
            8009,
            9105,
            8299
          ],
          "secondary_page_id": 8200,
          "secondary_rune_ids": [
            8210,
            8226
          ],
          "stat_mod_ids": [
            5007,
            5008,
            5011
          ],
          "play": 6,
          "win": 4,
          "pick_rate": 0.1818
        },
        {
          "id": 8010,
          "primary_page_id": 8000,
          "primary_rune_ids": [
            8010,
            8009,
            9105,
            8014
          ],
          "secondary_page_id": 8200,
          "secondary_rune_ids": [
            8210,
            8226
          ],
          "stat_mod_ids": [
            5005,
            5008,
            5001
          ],
          "play": 2,
          "win": 2,
          "pick_rate": 0.0606
        },
        {
          "id": 8010,
          "primary_page_id": 8000,
          "primary_rune_ids": [
            8010,
            8009,
            9105,
            8017
          ],
          "secondary_page_id": 8200,
          "secondary_rune_ids": [
            8210,
            8226
          ],
          "stat_mod_ids": [
            5005,
            5008,
            5011
          ],
          "play": 2,
          "win": 1,
          "pick_rate": 0.0606
        },
        {
          "id": 8010,
          "primary_page_id": 8000,
          "primary_rune_ids": [
            8010,
            8009,
            9105,
            8014
          ],
          "secondary_page_id": 8200,
          "secondary_rune_ids": [
            8210,
            8226
          ],
          "stat_mod_ids": [
            5008,
            5008,
            5001
          ],
          "play": 2,
          "win": 1,
          "pick_rate": 0.0606
        }
      ]
    },
    {
      "id": 8229,
      "primary_page_id": 8200,
      "secondary_page_id": 8000,
      "play": 18,
      "win": 8,
      "pick_rate": 0.0359,
      "builds": [
        {
          "id": 8229,
          "primary_page_id": 8200,
          "primary_rune_ids": [
            8229,
            8226,
            8234,
            8237
          ],
          "secondary_page_id": 8000,
          "secondary_rune_ids": [
            8009,
            8017
          ],
          "stat_mod_ids": [
            5005,
            5010,
            5011
          ],
          "play": 5,
          "win": 1,
          "pick_rate": 0.2778
        },
        {
          "id": 8229,
          "primary_page_id": 8200,
          "primary_rune_ids": [
            8229,
            8226,
            8210,
            8237
          ],
          "secondary_page_id": 8000,
          "secondary_rune_ids": [
            8009,
            8017
          ],
          "stat_mod_ids": [
            5005,
            5008,
            5011
          ],
          "play": 3,
          "win": 3,
          "pick_rate": 0.1667
        },
        {
          "id": 8229,
          "primary_page_id": 8200,
          "primary_rune_ids": [
            8229,
            8226,
            8210,
            8237
          ],
          "secondary_page_id": 8000,
          "secondary_rune_ids": [
            8009,
            8017
          ],
          "stat_mod_ids": [
            5008,
            5008,
            5011
          ],
          "play": 3,
          "win": 1,
          "pick_rate": 0.1667
        },
        {
          "id": 8229,
          "primary_page_id": 8200,
          "primary_rune_ids": [
            8229,
            8226,
            8210,
            8237
          ],
          "secondary_page_id": 8000,
          "secondary_rune_ids": [
            8009,
            8017
          ],
          "stat_mod_ids": [
            5008,
            5008,
            5001
          ],
          "play": 2,
          "win": 1,
          "pick_rate": 0.1111
        },
        {
          "id": 8229,
          "primary_page_id": 8200,
          "primary_rune_ids": [
            8229,
            8226,
            8234,
            8237
          ],
          "secondary_page_id": 8000,
          "secondary_rune_ids": [
            8009,
            8017
          ],
          "stat_mod_ids": [
            5005,
            5010,
            5001
          ],
          "play": 2,
          "win": 0,
          "pick_rate": 0.1111
        }
      ]
    }
  ],
  "core_items": [
    {
      "ids": [
        3070,
        6657,
        3040,
        3089
      ],
      "play": 73,
      "win": 45,
      "pick_rate": 0.2281
    },
    {
      "ids": [
        3070,
        6657,
        3040,
        3110
      ],
      "play": 48,
      "win": 29,
      "pick_rate": 0.15
    },
    {
      "ids": [
        3070,
        6657,
        3040,
        3157
      ],
      "play": 38,
      "win": 24,
      "pick_rate": 0.1188
    },
    {
      "ids": [
        3070,
        6657,
        3040,
        4629
      ],
      "play": 31,
      "win": 17,
      "pick_rate": 0.0969
    },
    {
      "ids": [
        3070,
        6657,
        3040,
        3135
      ],
      "play": 18,
      "win": 8,
      "pick_rate": 0.0563
    },
    {
      "ids": [
        3040,
        6655,
        3157
      ],
      "play": 11,
      "win": 7,
      "pick_rate": 0.0344
    },
    {
      "ids": [
        3040,
        6657,
        4629
      ],
      "play": 8,
      "win": 5,
      "pick_rate": 0.025
    },
    {
      "ids": [
        3040,
        6657,
        3089
      ],
      "play": 6,
      "win": 3,
      "pick_rate": 0.0188
    },
    {
      "ids": [
        3040,
        6657,
        3110
      ],
      "play": 6,
      "win": 5,
      "pick_rate": 0.0188
    },
    {
      "ids": [
        3070,
        6657,
        3040,
        3165
      ],
      "play": 5,
      "win": 4,
      "pick_rate": 0.0156
    },
    {
      "ids": [
        3040,
        6655,
        4645
      ],
      "play": 5,
      "win": 5,
      "pick_rate": 0.0156
    },
    {
      "ids": [
        3070,
        6655,
        3040,
        3089
      ],
      "play": 5,
      "win": 4,
      "pick_rate": 0.0156
    },
    {
      "ids": [
        3070,
        6657,
        3040,
        3102
      ],
      "play": 5,
      "win": 3,
      "pick_rate": 0.0156
    },
    {
      "ids": [
        3070,
        6657,
        3040,
        3116
      ],
      "play": 4,
      "win": 4,
      "pick_rate": 0.0125
    },
    {
      "ids": [
        3040,
        6655,
        3110
      ],
      "play": 4,
      "win": 2,
      "pick_rate": 0.0125
    }
  ],
  "boots": [
    {
      "ids": [
        3020
      ],
      "play": 211,
      "win": 116,
      "pick_rate": 0.4297
    },
    {
      "ids": [
        3158
      ],
      "play": 126,
      "win": 65,
      "pick_rate": 0.2566
    },
    {
      "ids": [
        3111
      ],
      "play": 66,
      "win": 31,
      "pick_rate": 0.1344
    },
    {
      "ids": [
        3047
      ],
      "play": 59,
      "win": 34,
      "pick_rate": 0.1202
    },
    {
      "ids": [
        3009
      ],
      "play": 29,
      "win": 14,
      "pick_rate": 0.0591
    }
  ],
  "starter_items": [
    {
      "ids": [
        2003,
        2003,
        3070
      ],
      "play": 376,
      "win": 191,
      "pick_rate": 0.7176
    },
    {
      "ids": [
        1056,
        2003,
        2003
      ],
      "play": 114,
      "win": 62,
      "pick_rate": 0.2176
    },
    {
      "ids": [
        1027,
        2031
      ],
      "play": 20,
      "win": 9,
      "pick_rate": 0.0382
    },
    {
      "ids": [
        1056,
        2003,
        2003,
        3070
      ],
      "play": 3,
      "win": 2,
      "pick_rate": 0.0057
    },
    {
      "ids": [
        1027,
        2003
      ],
      "play": 2,
      "win": 1,
      "pick_rate": 0.0038
    },
    {
      "ids": [
        1082,
        2003,
        2003,
        2003
      ],
      "play": 1,
      "win": 1,
      "pick_rate": 0.0019
    },
    {
      "ids": [
        1056,
        2003
      ],
      "play": 1,
      "win": 0,
      "pick_rate": 0.0019
    },
    {
      "ids": [
        1027,
        2003,
        2003,
        2003
      ],
      "play": 1,
      "win": 1,
      "pick_rate": 0.0019
    },
    {
      "ids": [
        1027,
        2003,
        2003,
        2003,
        2003
      ],
      "play": 1,
      "win": 1,
      "pick_rate": 0.0019
    },
    {
      "ids": [
        2003,
        3070
      ],
      "play": 1,
      "win": 0,
      "pick_rate": 0.0019
    },
    {
      "ids": [
        1054,
        2003
      ],
      "play": 1,
      "win": 0,
      "pick_rate": 0.0019
    },
    {
      "ids": [
        1027,
        2003,
        2003,
        3070
      ],
      "play": 1,
      "win": 1,
      "pick_rate": 0.0019
    },
    {
      "ids": [
        1001,
        1028,
        2003,
        2003,
        3070
      ],
      "play": 1,
      "win": 1,
      "pick_rate": 0.0019
    },
    {
      "ids": [
        1027,
        1056,
        2003,
        2003
      ],
      "play": 1,
      "win": 0,
      "pick_rate": 0.0019
    }
  ],
  "last_items": [
    {
      "ids": [
        3040
      ],
      "play": 416,
      "win": 224,
      "pick_rate": 0.8946
    },
    {
      "ids": [
        6657
      ],
      "play": 361,
      "win": 194,
      "pick_rate": 0.7763
    },
    {
      "ids": [
        3089
      ],
      "play": 131,
      "win": 82,
      "pick_rate": 0.2817
    },
    {
      "ids": [
        3110
      ],
      "play": 85,
      "win": 53,
      "pick_rate": 0.1828
    },
    {
      "ids": [
        3157
      ],
      "play": 77,
      "win": 51,
      "pick_rate": 0.1656
    },
    {
      "ids": [
        4629
      ],
      "play": 65,
      "win": 32,
      "pick_rate": 0.1398
    },
    {
      "ids": [
        6655
      ],
      "play": 53,
      "win": 28,
      "pick_rate": 0.114
    },
    {
      "ids": [
        3135
      ],
      "play": 49,
      "win": 24,
      "pick_rate": 0.1054
    },
    {
      "ids": [
        3070
      ],
      "play": 44,
      "win": 18,
      "pick_rate": 0.0946
    },
    {
      "ids": [
        3916
      ],
      "play": 42,
      "win": 17,
      "pick_rate": 0.0903
    },
    {
      "ids": [
        3102
      ],
      "play": 19,
      "win": 13,
      "pick_rate": 0.0409
    },
    {
      "ids": [
        2420
      ],
      "play": 18,
      "win": 12,
      "pick_rate": 0.0387
    },
    {
      "ids": [
        1082
      ],
      "play": 15,
      "win": 8,
      "pick_rate": 0.0323
    },
    {
      "ids": [
        3165
      ],
      "play": 14,
      "win": 10,
      "pick_rate": 0.0301
    },
    {
      "ids": [
        4645
      ],
      "play": 14,
      "win": 11,
      "pick_rate": 0.0301
    },
    {
      "ids": [
        3116
      ],
      "play": 8,
      "win": 6,
      "pick_rate": 0.0172
    },
    {
      "ids": [
        6653
      ],
      "play": 6,
      "win": 3,
      "pick_rate": 0.0129
    },
    {
      "ids": [
        3041
      ],
      "play": 6,
      "win": 6,
      "pick_rate": 0.0129
    },
    {
      "ids": [
        3003
      ],
      "play": 5,
      "win": 3,
      "pick_rate": 0.0108
    },
    {
      "ids": [
        8020
      ],
      "play": 5,
      "win": 1,
      "pick_rate": 0.0108
    },
    {
      "ids": [
        4646
      ],
      "play": 3,
      "win": 2,
      "pick_rate": 0.0065
    },
    {
      "ids": [
        3137
      ],
      "play": 3,
      "win": 1,
      "pick_rate": 0.0065
    },
    {
      "ids": [
        4401
      ],
      "play": 3,
      "win": 3,
      "pick_rate": 0.0065
    },
    {
      "ids": [
        3065
      ],
      "play": 2,
      "win": 2,
      "pick_rate": 0.0043
    },
    {
      "ids": [
        3143
      ],
      "play": 1,
      "win": 1,
      "pick_rate": 0.0022
    },
    {
      "ids": [
        6665
      ],
      "play": 1,
      "win": 0,
      "pick_rate": 0.0022
    },
    {
      "ids": [
        2503
      ],
      "play": 1,
      "win": 0,
      "pick_rate": 0.0022
    },
    {
      "ids": [
        4633
      ],
      "play": 1,
      "win": 0,
      "pick_rate": 0.0022
    },
    {
      "ids": [
        3742
      ],
      "play": 1,
      "win": 0,
      "pick_rate": 0.0022
    }
  ]
}